Workbook
Name \A: [1]A!$D$9:$D$53
Name ____MES1: '[2]DATOS DE OBRA'!#REF!
Name ___MES1: '[3]DATOS DE OBRA'!#REF!
Name ___PAG1: #REF!
Name __MES1: '[4]DATOS DE OBRA'!#REF!
Name __PAG1: #REF!
Name _MES1: '[3]DATOS DE OBRA'!#REF!
Name _MET1: #REF!
Name _MET2: #REF!
Name _PAG1: #REF!
Name A: [5]AreaLaguna!#REF!
Name A_1: #REF!
Name A_10: #REF!
Name A_11: #REF!
Name A_12: #REF!
Name A_13: #REF!
Name A_14: #REF!
Name A_15: #REF!
Name A_16: #REF!
Name A_17: #REF!
Name A_18: #REF!
Name A_19: #REF!
Name A_2: #REF!
Name A_20: #REF!
Name A_21: #REF!
Name A_22: #REF!
Name A_3: #REF!
Name A_4: #REF!
Name A_5: #REF!
Name A_6: #REF!
Name A_7: #REF!
Name A_8: #REF!
Name A_9: #REF!
Name A_impresión_IM: [6]Lagsram2!#REF!
Name aA: #REF!
Name aAA: #REF!
Name aB: #REF!
Name aC: #REF!
Name ACE: [1]A!$D$38
Name ACERO: [1]A!$D$70:$D$71
Name ACOM_CC: #REF!
Name ACOM_SC: #REF!
Name aD: #REF!
Name ADICIONAL: #REF!
Name ARENA: [1]A!$D$55:$D$56
Name ARMADOS: #REF!
Name ASAS: #REF!
Name BO_ACERO: [1]A!$D$37
Name BO_ARENA: [1]A!$D$21
Name BO_CEMENTO: [1]A!$D$27
Name BO_FORMALETA: [1]A!$D$33
Name BO_GRAVA: [1]A!$D$24
Name BO_OTROS: [1]A!$D$30
Name BO_SUMINISTRO: [1]A!$D$41
Name Cambio: #REF!
Name CAP: #REF!
Name CEMENTO: [1]A!$D$61:$D$62
Name CONDUC: #REF!
Name CONTRATISTA: CONCATENATE(": ",[8]FICHA!$E$8)
Name Costos: #REF!

Sheet RES. VALO
B2: RESUMEN DE LA VALORIZACIÓN N° 03 (01 AL 31 DE DICIEMBRE 2025)
B4: OBRA: | C4: =+FICHA!E4 -> "CONSTRUCCION DE NICHO, COLUMBARIO Y CREMATORIO; REMODELACION DE VELATORIO; EN EL (LA) CEMENTERIO MUNICIPAL EN EL CENTRO POBLADO SANTIAGO DE SURCO, DISTRITO DE SANTIAGO DE SURCO, PROVINCIA LIMA, DEPARTAMENTO LIMA" CUI N| 2658565 - ETAPA COLUMBARIO.
B5: UBICACIÓN: | C5: SURCO PUEBLO
B6: CONTRATISTA: | C6: CONSORCIO LIMA
B7: SUPERVISIÓN: | C7: ING. JOSE ISMAEL MOSCOSO PINGO
B8: MES: | C8: 45962
B10: ITEM | C10: CONCEPTOS | D10: MONTO (S/.)
B11: 1 | C11: VALORIZACIÓN (V) | D11: =+VALO!K565 -> 207432.97
B12: 2 | C12: REAJUSTES (R) | D12: =+Reajuste!J25 -> 0
B13: 3 | C13: DEDUCCIONES
B14: 3.1 | C14: Deducción de reajuste que no corresponde por adelanto directo | D14: 0
B15: 3.2 | C15: Deducción de reajuste que no corresponde por adelanto para materiales | D15: 0
C16: TOTAL DEDUCCIONES (D) | D16: =+D14+D15 -> 0
C17: VALORIZACIÓN BRUTA (VB=V+R-D) | D17: =+D11+D12-D16 -> 207432.97
B18: 4 | C18: AMORTIZACIONES
B19: 4.1 | C19: Amortización por adelanto directo | D19: 0
B20: 4.2 | C20: Amortización por adelanto para materiales | D20: 0
C21: TOTAL DE AMORTIZACIONES (A) | D21: =ROUND(D19+D20,2) -> 0
B22: VALORIZACIÓN NETA (VN=VB-A) | D22: =ROUND(D17-D21,2) -> 207432.97
B23: 5.1 | C23: MULTA | D23: 0
B24: 5.2 | C24: MONTO A PAGAR A LA CONTRATISTA | D24: =+D22 -> 207432.97
B25: IGV (18.00%) | D25: =+ROUND(D24*0.18,2) -> 37337.93
C26: MONTO TOTAL A PAGAR AL CONTRATISTA | D26: =+D24+D25 -> 244770.9
B27: 5.3 | C27: RETENCIONES 10 % (YA SE COMPLETÓ) | D27: 0
B28: TOTAL A PAGAR AL CONTRATISTA (VN+IGV-R) | D28: =+D24+D25-D27 -> 244770.9
C31: perfecto VLIZACION 01

Sheet FICHA
B2: I.- FICHA DE IDENTIFICACIÓN DE LA OBRA
B3: VALORIZACIÓN CONTRACTUAL DE OBRA Nº 03 (01 al 31 de DICIEMBRE) | E3: DICIEMBRE 2025
B4: 1 | C4: Proyecto | D4: : | E4: "CONSTRUCCION DE NICHO, COLUMBARIO Y CREMATORIO; REMODELACION DE VELATORIO; EN EL (LA) CEMENTERIO MUNICIPAL EN EL CENTRO POBLADO SANTIAGO DE SURCO, DISTRITO DE SANTIAGO DE SURCO, PROVINCIA LIMA, DEPARTAMENTO LIMA" CUI N| 2658565 - ETAPA COLUMBARIO.
B5: 2 | C5: Ubicación | D5: : | E5: DISTRITO DE SANTIAGO DE SURCO
C6: Area Geografica (Según INEI) | D6: : | E6: 2
B7: 3 | C7: Metas | D7: : | E7: CONSTRUCCION DE CREMATORIO, COLUMBARIO Y VELATORIO EN EL CEMENTERIO MUNICIPAL DE SURCO
B8: 4 | C8: Entidad Contratante | D8: : | E8: MUNICIPALIDAD DISTRITAL DE SANTIAGO DE SURCO
B9: 5 | C9: Contratista | D9: : | E9: CONSORCIO LIMA
B10: =+B9+1 -> 6 | C10: Supervisor | D10: : | E10: ING. JOSE ISMAEL MOSCOSO PINGO | G10: CIP N°259230
B11: =+B10+1 -> 7 | C11: Residente | D11: : | E11: ING. GUIDO JAVIER VALVERDE TRUJILLO | G11: CIP N° 58998
B12: =+B11+1 -> 8 | C12: Financiamiento | D12: : | E12: =+E8 -> MUNICIPALIDAD DISTRITAL DE SANTIAGO DE SURCO
B13: =+B12+1 -> 9 | C13: Modalidad de Ejecución | D13: : | E13: Administración Indirecta: CONTRATA
B14: =+B13+1 -> 10 | C14: Mecanismo de Contratación | D14: : | E14: ADJUDICACION PUBLICA ABREVIADA
B15: =+B14+1 -> 11 | C15: Licitiación Pública | D15: : | E15: 004-2025-CS-MSS-PRIMERA CONVOCATORIA
B16: =+B15+1 -> 12 | C16: Contrato Nº | D16: : | E16: 037-2025-GAF/MSS
B17: =+B16+1 -> 13 | C17: Sistema de Contratación | D17: : | E17: SUMA ALZADA
B18: =+B17+1 -> 14 | C18: Presupuesto base, con IGV y Fecha | D18: : | E18: 1821179.8 | G18: 45809
B19: =+B18+1 -> 15 | C19: Presupuesto base, sin IGV y Fecha | D19: : | E19: =E18/1.18 -> 1543372.7
B20: 16 | C20: Monto del contrato, con IGV | D20: : | E20: 1730120.8
B21: =+B20+1 -> 17 | C21: Monto del contrato, sin IGV | D21: : | E21: =ROUND(E20/1.18,2) -> 1466204.1
B22: =+B21+1 -> 18 | C22: Plazo de ejecución, en d. c. | D22: : | E22: 120
B23: =+B22+1 -> 19 | C23: Plazo de ejecución según Bases Lic., en dias calendario | D23: : | E23: =E22&" Días Calendario" -> 120 Días Calendario
B24: 20 | C24: Fecha de Firma de Contrato de obra | D24: : | E24: 45937
B25: =+B24+1 -> 21 | C25: Entrega de terreno | D25: : | E25: 45948
B26: =+B25+1 -> 22 | C26: Inicio oficial de plazo | D26: : | E26: 45954
B27: =+B26+1 -> 23 | C27: Término original programado de obra | D27: : | E27: =E26+E22-1 -> 46073
B28: =+B27+1 -> 24 | C28: Término vigente programado de obra | D28: : | E28: =E26+E22-1 -> 46073
B29: =+B28+1 -> 25 | C29: Avance Real Acumulado | D29: : | E29: =+VALO!N570 -> 0.72547563
B30: =+B29+1 -> 26 | C30: Avance Programado Acumulado | D30: : | E30: =+'C.G. AVANCE DE OBRA'!G16 -> 0.63343707
B31: =+B30+1 -> 27 | C31: Situación de la obra respecto del avance | D31: : | E31: =IF(E29>E30,"OBRA ADELANTADA",IF(E29=E30,"OBRA TERMINADA","OBRA ATRASADA")) -> OBRA ADELANTADA | F31: =ABS(E29-E30) -> 0.092038563
B38: PERFECTOOO

Sheet C.G. AVANCE DE OBRA
B2: CONTROL GENERAL DE AVANCE DE OBRA (01 AL 31 DE DICIEMBRE)
B5: ENTIDAD | C5: MUNICIPALIDAD DISTRITAL DE SANTIAGO DE SURCO | I5: MONTO REFERENCIAL | J5: =+FICHA!E18 -> 1821179.8
B6: CONTRATO DE OBRA | C6: =+FICHA!E16 -> 037-2025-GAF/MSS | I6: MONTO CONTRATADO | J6: =+FICHA!E20 -> 1730120.8
B7: OBRA | C7: =+FICHA!E4 -> "CONSTRUCCION DE NICHO, COLUMBARIO Y CREMATORIO; REMODELACION DE VELATORIO; EN EL (LA) CEMENTERIO MUNICIPAL EN EL CENTRO POBLADO SANTIAGO DE SURCO, DISTRITO DE SANTIAGO DE SURCO, PROVINCIA LIMA, DEPARTAMENTO LIMA" CUI N| 2658565 - ETAPA COLUMBARIO. | I7: PLAZO DE EJECUCIÓN VIGENTE | J7: =+FICHA!E23 -> 120 Días Calendario
B8: CONTRATISTA | C8: =+FICHA!E9 -> CONSORCIO LIMA | I8: FCHA DE INICIO DE OBRA | J8: =+FICHA!E26 -> 45954
B9: SUPERVISIÓN | C9: =+FICHA!E10 -> ING. JOSE ISMAEL MOSCOSO PINGO | I9: FECHA DE TERMINO DE OBRA | J9: =+FICHA!E27 -> 46073
B11: N° | C11: MES | D11: PROGRAMADO | H11: EJECUTADO | L11: SITUACIÓN DE OBRA | M11: OBSERVACION
D12: MENSUAL | E12: ACUMULADO | F12: % MENSUAL | G12: % ACUMULADO | H12: MENSUAL | I12: ACUMULADO | J12: % MENSUAL | K12: % ACUMULADO | M12: % PROGRAMADO ACUMULADO | N12: % EJECUTADO ACUMULADO | O12: CONCLUSIÓN
B14: 1 | C14: =+'CURVA S'!E29 -> 45939 | D14: 303729.84 | E14: =+D14 -> 303729.84 | F14: =+D14/$J$6 -> 0.17555412 | G14: =+F14 -> 0.17555412 | H14: 389969.06 | I14: =+H14 -> 389969.06 | J14: 0.2253999 | K14: =+J14 -> 0.2253999 | L14: adelantada | M14: =+G14 -> 0.17555412 | N14: =+K14 -> 0.2253999 | O14: La obra está sin inconveniente
B15: 2 | C15: =+'CURVA S'!E62 -> 45962 | D15: 307642.3 | E15: =+E14+D15 -> 611372.14 | F15: =+D15/$J$6 -> 0.1778155 | G15: =+G14+F15 -> 0.35336962 | H15: 620420.54 | I15: =+I14+H15 -> 1010389.6 | J15: 0.35859954 | K15: =+K14+J15 -> 0.58399944 | L15: adelantada | M15: =+G15 -> 0.35336962 | N15: =+K15 -> 0.58399944 | O15: La obra está sin inconveniente
B16: 3 | C16: =+'CURVA S'!E63 -> 45992 | D16: 484550.53 | E16: =+E15+D16 -> 1095922.7 | F16: =+D16/$J$6 -> 0.28006745 | G16: =+G15+F16 -> 0.63343707 | H16: =+VALO!K568 -> 244770.9 | I16: =+I15+H16 -> 1255160.5 | J16: =+VALO!K569 -> 0.14147619 | K16: =+K15+J16 -> 0.72547563 | L16: adelantada | M16: =+G16 -> 0.63343707 | N16: =+K16 -> 0.72547563 | O16: La obra está sin inconveniente
B17: 4 | C17: =+'CURVA S'!E64 -> 46023 | D17: 374272.7 | E17: =+E16+D17 -> 1470195.4 | F17: =+D17/$J$6 -> 0.21632749 | G17: =+G16+F17 -> 0.84976456
B18: 5 | C18: =+'CURVA S'!E65 -> 46054 | D18: 259925.47 | E18: =+E17+D18 -> 1730120.8 | F18: =+D18/$J$6 -> 0.15023544 | G18: =+G17+F18 -> 1
E24: =+E18*0.3 -> 519036.25

Sheet VALO
A2: VALORIZACIÓN N° 03 (01 AL 31 DE DICIEMBRE DE 2025)
A4: CONTRATISTA | B4: CONSORCIO LIMA | G4: MONTO REFERENCIAL | M4: =+FICHA!E18 -> 1821179.8
A5: SUPERVISIÓN | B5: ING. JOSE ISMAEL MOSCOSO PINGO | G5: MONTO CONTRATADO | M5: 1730120.8
A6: RESIDENTE | B6: ING. GUIDO JAVIER VALVERDE TRUJILLO | G6: PLAZO DE EJECUCION | M6: 120 DÍAS CALENDARIOS
A7: SUPERVISOR | B7: ING. JOSE ISMAEL MOSCOSO PINGO | G7: ENTIDAD CONTRATANTE | M7: MUNICIPALIDAD DISTRITAL DE SANTIAGO DE SURCO
A9: ITEM | B9: PARTIDA | C9: PRESUPUESTO BASE | G9: AVANCE DE EJECUCIÓN
G13: ANTERIOR | J13: ACTUAL | M13: ACUMULADO | P13: SALDOS
C14: UND | D14: METRADO | E14: PU | F14: SUB TOTAL | G14: METRADO | H14: VALOR S/. | I14: % | J14: METRADO | K14: VALOR S/. | L14: % | M14: METRADO | N14: VALOR S/. | O14: % | P14: METRADO | Q14: VALOR S/. | R14: %
A15: 1 | B15: OBRAS PROVISIONALES, TRABAJOS PRELIMINARES, SEGURIDAD Y SALUD | F15: =+F16+F30+F44+F51+F61 -> 77708.1
A16: 01.01 | B16: OBRAS PROVISIONALES | F16: =+F17+F24 -> 16918.48
A17: 01.01.01 | B17: CONSTRUCCIONES PROVISIONALES | F17: =SUM(F18:F23) -> 11209.46
A18: 01.01.01.01 | B18: CARTEL DE IDENTIFICACION DE LA OBRA DE 3.60X2.40 m | C18: und | D18: 1 | E18: 2350.85 | F18: =+ROUND((D18*E18),2) -> 2350.85 | G18: 1 | H18: =G18*E18 -> 2350.85 | I18: =+G18/D18 -> 1 | K18: =J18*E18 -> 0 | L18: =+J18/D18 -> 0 | M18: =+G18+J18 -> 1 | N18: =M18*E18 -> 2350.85 | O18: =+M18/D18 -> 1 | P18: =+D18-M18 -> 0 | Q18: =P18*E18 -> 0 | R18: =+P18/D18 -> 0 | S18: =N18+Q18 -> 2350.85 | T18: =F18-S18 -> 0
A19: 01.01.01.02 | B19: CERCO PERIMETRICO PROVISIONAL DE MALLA RASCHELL H=2.10M | C19: m | D19: 48.86 | E19: 27.65 | F19: =+ROUND((D19*E19),2) -> 1350.98 | G19: 48.86 | H19: =G19*E19 -> 1350.979 | I19: =+G19/D19 -> 1 | K19: =J19*E19 -> 0 | L19: =+J19/D19 -> 0 | M19: =+G19+J19 -> 48.86 | N19: =M19*E19 -> 1350.979 | O19: =+M19/D19 -> 1 | P19: =+D19-M19 -> 0 | Q19: =P19*E19 -> 0 | R19: =+P19/D19 -> 0 | S19: =N19+Q19 -> 1350.979 | T19: =F19-S19 -> 0.001
A20: 01.01.01.03 | B20: CERCO PERIMETRICO PROVISIONAL METALICO H=2.10M PROVISIONAL | C20: m | D20: 48.86 | E20: 42.57 | F20: =+ROUND((D20*E20),2) -> 2079.97 | G20: 48.86 | H20: =G20*E20 -> 2079.9702 | I20: =+G20/D20 -> 1 | K20: =J20*E20 -> 0 | L20: =+J20/D20 -> 0 | M20: =+G20+J20 -> 48.86 | N20: =M20*E20 -> 2079.9702 | O20: =+M20/D20 -> 1 | P20: =+D20-M20 -> 0 | Q20: =P20*E20 -> 0 | R20: =+P20/D20 -> 0 | S20: =N20+Q20 -> 2079.9702 | T20: =F20-S20 -> -0.0002
A21: 01.01.01.04 | B21: ALMACEN, OFICINA Y CASETA DE GUARDIANIA DE TRIPLAY | C21: m2 | D21: 26 | E21: 88.91 | F21: =+ROUND((D21*E21),2) -> 2311.66 | G21: 26 | H21: =G21*E21 -> 2311.66 | I21: =+G21/D21 -> 1 | K21: =J21*E21 -> 0 | L21: =+J21/D21 -> 0 | M21: =+G21+J21 -> 26 | N21: =M21*E21 -> 2311.66 | O21: =+M21/D21 -> 1 | P21: =+D21-M21 -> 0 | Q21: =P21*E21 -> 0 | R21: =+P21/D21 -> 0 | S21: =N21+Q21 -> 2311.66 | T21: =F21-S21 -> 0
A22: 01.01.01.05 | B22: TRANSPORTES DE MAQUINARIAS, EQUIPO Y HERRAMIENTAS A OBRA | C22: glb | D22: 1 | E22: 2280 | F22: =+ROUND((D22*E22),2) -> 2280 | G22: 1 | H22: =G22*E22 -> 2280 | I22: =+G22/D22 -> 1 | K22: =J22*E22 -> 0 | L22: =+J22/D22 -> 0 | M22: =+G22+J22 -> 1 | N22: =M22*E22 -> 2280 | O22: =+M22/D22 -> 1 | P22: =+D22-M22 -> 0 | Q22: =P22*E22 -> 0 | R22: =+P22/D22 -> 0 | S22: =N22+Q22 -> 2280 | T22: =F22-S22 -> 0
A23: 01.01.01.06 | B23: TRANSPORTES DE MATERIALES | C23: glb | D23: 1 | E23: 836 | F23: =+ROUND((D23*E23),2) -> 836 | G23: 1 | H23: =G23*E23 -> 836 | I23: =+G23/D23 -> 1 | K23: =J23*E23 -> 0 | L23: =+J23/D23 -> 0 | M23: =+G23+J23 -> 1 | N23: =M23*E23 -> 836 | O23: =+M23/D23 -> 1 | P23: =+D23-M23 -> 0 | Q23: =P23*E23 -> 0 | R23: =+P23/D23 -> 0 | S23: =N23+Q23 -> 836 | T23: =F23-S23 -> 0
A24: 01.01.02 | B24: INSTALACIONES PROVISIONALES | F24: =SUM(F25:F29) -> 5709.02
A25: 01.01.02.01 | B25: ALQUILER DE BAÑOS QUIMICOS PORTATILES | C25: mes | D25: 4 | E25: 570 | F25: =+ROUND((D25*E25),2) -> 2280 | G25: 2 | H25: =G25*E25 -> 1140 | I25: =+G25/D25 -> 0.5 | J25: 1 | K25: =J25*E25 -> 570 | L25: =+J25/D25 -> 0.25 | M25: =+G25+J25 -> 3 | N25: =M25*E25 -> 1710 | O25: =+M25/D25 -> 0.75 | P25: =+D25-M25 -> 1 | Q25: =P25*E25 -> 570 | R25: =+P25/D25 -> 0.25 | S25: =N25+Q25 -> 2280 | T25: =F25-S25 -> 0
A26: 01.01.02.02 | B26: SUM. E INST. PARA EL PUNTO DE AGUA EN OBRA | C26: glb | D26: 1 | E26: 446.02 | F26: =+ROUND((D26*E26),2) -> 446.02 | G26: 1 | H26: =G26*E26 -> 446.02 | I26: =+G26/D26 -> 1 | K26: =J26*E26 -> 0 | L26: =+J26/D26 -> 0 | M26: =+G26+J26 -> 1 | N26: =M26*E26 -> 446.02 | O26: =+M26/D26 -> 1 | P26: =+D26-M26 -> 0 | Q26: =P26*E26 -> 0 | R26: =+P26/D26 -> 0 | S26: =N26+Q26 -> 446.02 | T26: =F26-S26 -> 0
A27: 01.01.02.03 | B27: SUM. E INST. PARA EL PUNTO DE ENERGIA EN OBRA | C27: glb | D27: 1 | E27: 380 | F27: =+ROUND((D27*E27),2) -> 380 | G27: 1 | H27: =G27*E27 -> 380 | I27: =+G27/D27 -> 1 | K27: =J27*E27 -> 0 | L27: =+J27/D27 -> 0 | M27: =+G27+J27 -> 1 | N27: =M27*E27 -> 380 | O27: =+M27/D27 -> 1 | P27: =+D27-M27 -> 0 | Q27: =P27*E27 -> 0 | R27: =+P27/D27 -> 0 | S27: =N27+Q27 -> 380 | T27: =F27-S27 -> 0
A28: 01.01.02.04 | B28: AGUA PROVISIONAL PARA LA CONSTRUCCION | C28: mes | D28: 4 | E28: 285 | F28: =+ROUND((D28*E28),2) -> 1140 | G28: 2 | H28: =G28*E28 -> 570 | I28: =+G28/D28 -> 0.5 | J28: 1 | K28: =J28*E28 -> 285 | L28: =+J28/D28 -> 0.25 | M28: =+G28+J28 -> 3 | N28: =M28*E28 -> 855 | O28: =+M28/D28 -> 0.75 | P28: =+D28-M28 -> 1 | Q28: =P28*E28 -> 285 | R28: =+P28/D28 -> 0.25 | S28: =N28+Q28 -> 1140 | T28: =F28-S28 -> 0
A29: 01.01.02.05 | B29: ENERGIA ELECTRICA PROVISIONAL | C29: mes | D29: 4 | E29: 365.75 | F29: =+ROUND((D29*E29),2) -> 1463 | G29: 2 | H29: =G29*E29 -> 731.5 | I29: =+G29/D29 -> 0.5 | J29: 1 | K29: =J29*E29 -> 365.75 | L29: =+J29/D29 -> 0.25 | M29: =+G29+J29 -> 3 | N29: =M29*E29 -> 1097.25 | O29: =+M29/D29 -> 0.75 | P29: =+D29-M29 -> 1 | Q29: =P29*E29 -> 365.75 | R29: =+P29/D29 -> 0.25 | S29: =N29+Q29 -> 1463 | T29: =F29-S29 -> 0
A30: 01.02 | B30: TRABAJOS PRELIMINARES | F30: =+F31+F34+F42 -> 4767.26 | T30: =F30-S30 -> #VALUE!
A31: 01.02.01 | B31: CREMATORIO | F31: =SUM(F32:F33) -> 1719.98 | T31: =F31-S31 -> #VALUE!
A32: 01.02.01.01 | B32: DESBROCE Y LIMPIEZA MANUAL DEL TERRENO | C32: m2 | D32: 163 | E32: 5.13 | F32: =+ROUND((D32*E32),2) -> 836.19 | G32: 163 | H32: =G32*E32 -> 836.19 | I32: =+G32/D32 -> 1 | K32: =J32*E32 -> 0 | L32: =+J32/D32 -> 0 | M32: =+G32+J32 -> 163 | N32: =M32*E32 -> 836.19 | O32: =+M32/D32 -> 1 | P32: =+D32-M32 -> 0 | Q32: =P32*E32 -> 0 | R32: =+P32/D32 -> 0 | S32: =N32+Q32 -> 836.19 | T32: =F32-S32 -> 0
A33: 01.02.01.02 | B33: ELIMINACION DE MALEZA Y ARBUSTOS DE FACIL EXTRACCION | C33: m3 | D33: 28.2 | E33: 31.34 | F33: =+ROUND((D33*E33),2) -> 883.79 | G33: 28.2 | H33: =G33*E33 -> 883.788 | I33: =+G33/D33 -> 1 | K33: =J33*E33 -> 0 | L33: =+J33/D33 -> 0 | M33: =+G33+J33 -> 28.2 | N33: =M33*E33 -> 883.788 | O33: =+M33/D33 -> 1 | P33: =+D33-M33 -> 0 | Q33: =P33*E33 -> 0 | R33: =+P33/D33 -> 0 | S33: =N33+Q33 -> 883.788 | T33: =F33-S33 -> 0.002
A34: 01.02.02 | B34: VELATORIO | F34: =SUM(F35:F41) -> 2081.76 | S34: =N34+Q34 -> #VALUE! | T34: =F34-S34 -> #VALUE!
A35: 01.02.02.01 | B35: DEMOLICIÓN DE MUROS EXISTENTES | C35: m2 | D35: 30.39 | E35: 22.14 | F35: =+ROUND((D35*E35),2) -> 672.83 | G35: 30.39 | H35: =G35*E35 -> 672.8346 | I35: =+G35/D35 -> 1 | K35: =J35*E35 -> 0 | L35: =+J35/D35 -> 0 | M35: =+G35+J35 -> 30.39 | N35: =M35*E35 -> 672.8346 | O35: =+M35/D35 -> 1 | P35: =+D35-M35 -> 0 | Q35: =P35*E35 -> 0 | R35: =+P35/D35 -> 0 | S35: =N35+Q35 -> 672.8346 | T35: =F35-S35 -> -0.0046
A36: 01.02.02.02 | B36: DESMONTAJE DE APARATOS SANITARIOS EXISTENTES EN LA OFICINA DE ADMINISTRACIÓN | C36: glb | D36: 1 | E36: 31.49 | F36: =+ROUND((D36*E36),2) -> 31.49 | G36: 1 | H36: =G36*E36 -> 31.49 | I36: =+G36/D36 -> 1 | K36: =J36*E36 -> 0 | L36: =+J36/D36 -> 0 | M36: =+G36+J36 -> 1 | N36: =M36*E36 -> 31.49 | O36: =+M36/D36 -> 1 | P36: =+D36-M36 -> 0 | Q36: =P36*E36 -> 0 | R36: =+P36/D36 -> 0 | S36: =N36+Q36 -> 31.49 | T36: =F36-S36 -> 0
A37: 01.02.02.03 | B37: RETIRO DE CERÁMICO EXISTENTE EN LA OFICINA | C37: m2 | D37: 54.65 | E37: 15.11 | F37: =+ROUND((D37*E37),2) -> 825.76 | G37: 54.65 | H37: =G37*E37 -> 825.7615 | I37: =+G37/D37 -> 1 | K37: =J37*E37 -> 0 | L37: =+J37/D37 -> 0 | M37: =+G37+J37 -> 54.65 | N37: =M37*E37 -> 825.7615 | O37: =+M37/D37 -> 1 | P37: =+D37-M37 -> 0 | Q37: =P37*E37 -> 0 | R37: =+P37/D37 -> 0 | S37: =N37+Q37 -> 825.7615 | T37: =F37-S37 -> -0.0015
A38: 01.02.02.04 | B38: RETIRO DE PISO EXISTENTE EN NUEVA ZONA DE KITCHENETTE Y CANALETAS | C38: m2 | D38: 3.46 | E38: 26.75 | F38: =+ROUND((D38*E38),2) -> 92.56 | G38: 3.46 | H38: =G38*E38 -> 92.555 | I38: =+G38/D38 -> 1 | K38: =J38*E38 -> 0 | L38: =+J38/D38 -> 0 | M38: =+G38+J38 -> 3.46 | N38: =M38*E38 -> 92.555 | O38: =+M38/D38 -> 1 | P38: =+D38-M38 -> 0 | Q38: =P38*E38 -> 0 | R38: =+P38/D38 -> 0 | S38: =N38+Q38 -> 92.555 | T38: =F38-S38 -> 0.005
A39: 01.02.02.05 | B39: DESMONTAJE DE SISTEMAS ELECTRICOS, INC. SELLADO DE SALIDAS SEGÚN PLANO | C39: glb | D39: 1 | E39: 31.49 | F39: =+ROUND((D39*E39),2) -> 31.49 | G39: 1 | H39: =G39*E39 -> 31.49 | I39: =+G39/D39 -> 1 | K39: =J39*E39 -> 0 | L39: =+J39/D39 -> 0 | M39: =+G39+J39 -> 1 | N39: =M39*E39 -> 31.49 | O39: =+M39/D39 -> 1 | P39: =+D39-M39 -> 0 | Q39: =P39*E39 -> 0 | R39: =+P39/D39 -> 0 | S39: =N39+Q39 -> 31.49 | T39: =F39-S39 -> 0
A40: 01.02.02.06 | B40: DESMONTAJE DE SISTEMAS DE COMUNICACIONES Y REDES | C40: glb | D40: 1 | E40: 31.49 | F40: =+ROUND((D40*E40),2) -> 31.49 | G40: 1 | H40: =G40*E40 -> 31.49 | I40: =+G40/D40 -> 1 | K40: =J40*E40 -> 0 | L40: =+J40/D40 -> 0 | M40: =+G40+J40 -> 1 | N40: =M40*E40 -> 31.49 | O40: =+M40/D40 -> 1 | P40: =+D40-M40 -> 0 | Q40: =P40*E40 -> 0 | R40: =+P40/D40 -> 0 | S40: =N40+Q40 -> 31.49 | T40: =F40-S40 -> 0
A41: 01.02.02.07 | B41: ELIMINACION DE MATERIAL EXCEDENTE C/VOLQ. 15M3, D=10km | C41: m3 | D41: 12.64 | E41: 31.34 | F41: =+ROUND((D41*E41),2) -> 396.14 | G41: 12.64 | H41: =G41*E41 -> 396.1376 | I41: =+G41/D41 -> 1 | K41: =J41*E41 -> 0 | L41: =+J41/D41 -> 0 | M41: =+G41+J41 -> 12.64 | N41: =M41*E41 -> 396.1376 | O41: =+M41/D41 -> 1 | P41: =+D41-M41 -> 0 | Q41: =P41*E41 -> 0 | R41: =+P41/D41 -> 0 | S41: =N41+Q41 -> 396.1376 | T41: =F41-S41 -> 0.0024
A42: 01.02.03 | B42: COLUMBARIO | F42: =+F43 -> 965.52
A43: 01.02.03.01 | B43: DESBROCE Y LIMPIEZA MANUAL DEL TERRENO | C43: m2 | D43: 188.21 | E43: 5.13 | F43: =+ROUND((D43*E43),2) -> 965.52 | G43: 188.21 | H43: =G43*E43 -> 965.5173 | I43: =+G43/D43 -> 1 | K43: =J43*E43 -> 0 | L43: =+J43/D43 -> 0 | M43: =+G43+J43 -> 188.21 | N43: =M43*E43 -> 965.5173 | O43: =+M43/D43 -> 1 | P43: =+D43-M43 -> 0 | Q43: =P43*E43 -> 0 | R43: =+P43/D43 -> 0 | S43: =N43+Q43 -> 965.5173 | T43: =F43-S43 -> 0.0027
A44: 1.03 | B44: SEGURIDAD Y SALUD EN EL TRABAJO | F44: =SUM(F45:F50) -> 22523.25
A45: 01.03.01 | B45: ELABORACIÓN, IMPLEMENTACIÓN Y ADMINISTRACIÓN DEL PLAN DE SEGURIDAD Y SALUD EN EL TRABAJO | C45: glb | D45: 1 | E45: 120.76 | F45: =+ROUND((D45*E45),2) -> 120.76 | G45: 1 | H45: =G45*E45 -> 120.76 | I45: =+G45/D45 -> 1 | K45: =J45*E45 -> 0 | L45: =+J45/D45 -> 0 | M45: =+G45+J45 -> 1 | N45: =M45*E45 -> 120.76 | O45: =+M45/D45 -> 1 | P45: =+D45-M45 -> 0 | Q45: =P45*E45 -> 0 | R45: =+P45/D45 -> 0 | S45: =N45+Q45 -> 120.76 | T45: =F45-S45 -> 0
A46: 01.03.02 | B46: EQUIPOS DE PROTECCION INDIVIDUAL | C46: glb | D46: 1 | E46: 10384.45 | F46: =+ROUND((D46*E46),2) -> 10384.45 | G46: 0.5 | H46: =G46*E46 -> 5192.225 | I46: =+G46/D46 -> 0.5 | J46: 0.25 | K46: =J46*E46 -> 2596.1125 | L46: =+J46/D46 -> 0.25 | M46: =+G46+J46 -> 0.75 | N46: =M46*E46 -> 7788.3375 | O46: =+M46/D46 -> 0.75 | P46: =+D46-M46 -> 0.25 | Q46: =P46*E46 -> 2596.1125 | R46: =+P46/D46 -> 0.25 | S46: =N46+Q46 -> 10384.45 | T46: =F46-S46 -> 0
A47: 01.03.03 | B47: EQUIPOS DE PROTECCION COLECTIVA | C47: glb | D47: 1 | E47: 2375 | F47: =+ROUND((D47*E47),2) -> 2375 | G47: 0.5 | H47: =G47*E47 -> 1187.5 | I47: =+G47/D47 -> 0.5 | J47: 0.25 | K47: =J47*E47 -> 593.75 | L47: =+J47/D47 -> 0.25 | M47: =+G47+J47 -> 0.75 | N47: =M47*E47 -> 1781.25 | O47: =+M47/D47 -> 0.75 | P47: =+D47-M47 -> 0.25 | Q47: =P47*E47 -> 593.75 | R47: =+P47/D47 -> 0.25 | S47: =N47+Q47 -> 2375 | T47: =F47-S47 -> 0
A48: 01.03.04 | B48: SEÑALIZACIÓN TEMPORAL DE SEGURIDAD | C48: glb | D48: 1 | E48: 3349.7 | F48: =+ROUND((D48*E48),2) -> 3349.7 | G48: 0.5 | H48: =G48*E48 -> 1674.85 | I48: =+G48/D48 -> 0.5 | J48: 0.25 | K48: =J48*E48 -> 837.425 | L48: =+J48/D48 -> 0.25 | M48: =+G48+J48 -> 0.75 | N48: =M48*E48 -> 2512.275 | O48: =+M48/D48 -> 0.75 | P48: =+D48-M48 -> 0.25 | Q48: =P48*E48 -> 837.425 | R48: =+P48/D48 -> 0.25 | S48: =N48+Q48 -> 3349.7 | T48: =F48-S48 -> 0
A49: 01.03.05 | B49: CAPACITACION EN SEGURIDAD Y SALUD | C49: glb | D49: 1 | E49: 3800 | F49: =+ROUND((D49*E49),2) -> 3800 | G49: 0.5 | H49: =G49*E49 -> 1900 | I49: =+G49/D49 -> 0.5 | J49: 0.25 | K49: =J49*E49 -> 950 | L49: =+J49/D49 -> 0.25 | M49: =+G49+J49 -> 0.75 | N49: =M49*E49 -> 2850 | O49: =+M49/D49 -> 0.75 | P49: =+D49-M49 -> 0.25 | Q49: =P49*E49 -> 950 | R49: =+P49/D49 -> 0.25 | S49: =N49+Q49 -> 3800 | T49: =F49-S49 -> 0
A50: 01.03.06 | B50: RECURSOS PARA RESPUESTAS ANTE EMERGENCIAS | C50: glb | D50: 1 | E50: 2493.34 | F50: =+ROUND((D50*E50),2) -> 2493.34 | G50: 0.5 | H50: =G50*E50 -> 1246.67 | I50: =+G50/D50 -> 0.5 | J50: 0.25 | K50: =J50*E50 -> 623.335 | L50: =+J50/D50 -> 0.25 | M50: =+G50+J50 -> 0.75 | N50: =M50*E50 -> 1870.005 | O50: =+M50/D50 -> 0.75 | P50: =+D50-M50 -> 0.25 | Q50: =P50*E50 -> 623.335 | R50: =+P50/D50 -> 0.25 | S50: =N50+Q50 -> 2493.34 | T50: =F50-S50 -> 0
A51: 01.04 | B51: PLAN DE MANEJO AMBIENTAL | F51: =SUM(F52:F60) -> 32065.02
A52: 01.04.01 | B52: PROGRAMA DE PREVENCION Y MITIGACION AMBIENTAL | C52: glb | D52: 1 | E52: 8050.85 | F52: =+ROUND((D52*E52),2) -> 8050.85 | G52: 1 | H52: =G52*E52 -> 8050.85 | I52: =+G52/D52 -> 1 | K52: =J52*E52 -> 0 | L52: =+J52/D52 -> 0 | M52: =+G52+J52 -> 1 | N52: =M52*E52 -> 8050.85 | O52: =+M52/D52 -> 1 | P52: =+D52-M52 -> 0 | Q52: =P52*E52 -> 0 | R52: =+P52/D52 -> 0 | S52: =N52+Q52 -> 8050.85 | T52: =F52-S52 -> 0
A53: 01.04.02 | B53: PLAN DE MANEJO DE RESIDUOS SOLIDOS | C53: glb | D53: 1 | E53: 8050.85 | F53: =+ROUND((D53*E53),2) -> 8050.85 | G53: 0 | H53: =G53*E53 -> 0 | I53: =+G53/D53 -> 0 | J53: 1 | K53: =J53*E53 -> 8050.85 | L53: =+J53/D53 -> 1 | M53: =+G53+J53 -> 1 | N53: =M53*E53 -> 8050.85 | O53: =+M53/D53 -> 1 | P53: =+D53-M53 -> 0 | Q53: =P53*E53 -> 0 | R53: =+P53/D53 -> 0 | S53: =N53+Q53 -> 8050.85 | T53: =F53-S53 -> 0
A54: 01.04.03 | B54: PROGRAMA DE MONITOREO AMBIENTAL | C54: glb | D54: 1 | E54: 4025.43 | F54: =+ROUND((D54*E54),2) -> 4025.43 | G54: 0 | H54: =G54*E54 -> 0 | I54: =+G54/D54 -> 0 | J54: 1 | K54: =J54*E54 -> 4025.43 | L54: =+J54/D54 -> 1 | M54: =+G54+J54 -> 1 | N54: =M54*E54 -> 4025.43 | O54: =+M54/D54 -> 1 | P54: =+D54-M54 -> 0 | Q54: =P54*E54 -> 0 | R54: =+P54/D54 -> 0 | S54: =N54+Q54 -> 4025.43 | T54: =F54-S54 -> 0
A55: 01.04.04 | B55: PROGRAMA DE USO DE AGUA | C55: glb | D55: 1 | E55: 4023.37 | F55: =+ROUND((D55*E55),2) -> 4023.37 | G55: 0.5 | H55: =G55*E55 -> 2011.685 | I55: =+G55/D55 -> 0.5 | J55: 0.5 | K55: =J55*E55 -> 2011.685 | L55: =+J55/D55 -> 0.5 | M55: =+G55+J55 -> 1 | N55: =M55*E55 -> 4023.37 | O55: =+M55/D55 -> 1 | P55: =+D55-M55 -> 0 | Q55: =P55*E55 -> 0 | R55: =+P55/D55 -> 0 | S55: =N55+Q55 -> 4023.37 | T55: =F55-S55 -> 0
A56: 01.04.05 | B56: PROGRAMA DE EDUCACION, FORMACION Y CAPACITACION DE PERSONAL | C56: glb | D56: 1 | E56: 1127.64 | F56: =+ROUND((D56*E56),2) -> 1127.64 | G56: 0.5 | H56: =G56*E56 -> 563.82 | I56: =+G56/D56 -> 0.5 | J56: 0.5 | K56: =J56*E56 -> 563.82 | L56: =+J56/D56 -> 0.5 | M56: =+G56+J56 -> 1 | N56: =M56*E56 -> 1127.64 | O56: =+M56/D56 -> 1 | P56: =+D56-M56 -> 0 | Q56: =P56*E56 -> 0 | R56: =+P56/D56 -> 0 | S56: =N56+Q56 -> 1127.64 | T56: =F56-S56 -> 0
A57: 01.04.06 | B57: PROGRAMA DE SEGURIDAD Y SALUD OCUPACIONAL | C57: glb | D57: 1 | E57: 1610.17 | F57: =+ROUND((D57*E57),2) -> 1610.17 | G57: 0.5 | H57: =G57*E57 -> 805.085 | I57: =+G57/D57 -> 0.5 | J57: 0.5 | K57: =J57*E57 -> 805.085 | L57: =+J57/D57 -> 0.5 | M57: =+G57+J57 -> 1 | N57: =M57*E57 -> 1610.17 | O57: =+M57/D57 -> 1 | P57: =+D57-M57 -> 0 | Q57: =P57*E57 -> 0 | R57: =+P57/D57 -> 0 | S57: =N57+Q57 -> 1610.17 | T57: =F57-S57 -> 0
A58: 01.04.07 | B58: PLAN DE CONTINGENCIAS | C58: glb | D58: 1 | E58: 805.09 | F58: =+ROUND((D58*E58),2) -> 805.09 | G58: 0.5 | H58: =G58*E58 -> 402.545 | I58: =+G58/D58 -> 0.5 | J58: 0.5 | K58: =J58*E58 -> 402.545 | L58: =+J58/D58 -> 0.5 | M58: =+G58+J58 -> 1 | N58: =M58*E58 -> 805.09 | O58: =+M58/D58 -> 1 | P58: =+D58-M58 -> 0 | Q58: =P58*E58 -> 0 | R58: =+P58/D58 -> 0 | S58: =N58+Q58 -> 805.09 | T58: =F58-S58 -> 0
A59: 01.04.08 | B59: PROGRAMA DE CONTROL DE VIGILANCIA SANITARIA PARA PLAGAS Y VECTORES | C59: glb | D59: 1 | E59: 346.19 | F59: =+ROUND((D59*E59),2) -> 346.19 | G59: 0 | H59: =G59*E59 -> 0 | I59: =+G59/D59 -> 0 | J59: 1 | K59: =J59*E59 -> 346.19 | L59: =+J59/D59 -> 1 | M59: =+G59+J59 -> 1 | N59: =M59*E59 -> 346.19 | O59: =+M59/D59 -> 1 | P59: =+D59-M59 -> 0 | Q59: =P59*E59 -> 0 | R59: =+P59/D59 -> 0 | S59: =N59+Q59 -> 346.19 | T59: =F59-S59 -> 0
A60: 01.04.09 | B60: PROGRAMA DE CIERRE | C60: glb | D60: 1 | E60: 4025.43 | F60: =+ROUND((D60*E60),2) -> 4025.43 | G60: 0 | H60: =G60*E60 -> 0 | I60: =+G60/D60 -> 0 | K60: =J60*E60 -> 0 | L60: =+J60/D60 -> 0 | M60: =+G60+J60 -> 0 | N60: =M60*E60 -> 0 | O60: =+M60/D60 -> 0 | P60: =+D60-M60 -> 1 | Q60: =P60*E60 -> 4025.43 | R60: =+P60/D60 -> 1 | S60: =N60+Q60 -> 4025.43 | T60: =F60-S60 -> 0
A61: 01.05 | B61: TRAZO Y REPLANTEO | F61: =SUM(F62:F63) -> 1434.09
A62: 01.05.01 | B62: TRAZO NIVELACION Y REPLANTEO INICIAL | C62: m2 | D62: 405.11 | E62: 1.81 | F62: =+ROUND((D62*E62),2) -> 733.25 | G62: 405.11 | H62: =G62*E62 -> 733.2491 | I62: =+G62/D62 -> 1 | K62: =J62*E62 -> 0 | L62: =+J62/D62 -> 0 | M62: =+G62+J62 -> 405.11 | N62: =M62*E62 -> 733.2491 | O62: =+M62/D62 -> 1 | P62: =+D62-M62 -> 0 | Q62: =P62*E62 -> 0 | R62: =+P62/D62 -> 0 | S62: =N62+Q62 -> 733.2491 | T62: =F62-S62 -> 0.0009
A63: 01.05.02 | B63: TRAZO NIVELACION Y REPLANTEO DURANTE EL PROCESO | C63: m2 | D63: 405.11 | E63: 1.73 | F63: =+ROUND((D63*E63),2) -> 700.84 | G63: 202.5575 | H63: =G63*E63 -> 350.42448 | I63: =+G63/D63 -> 0.50000617 | J63: =+D63/4 -> 101.2775 | K63: =J63*E63 -> 175.21008 | L63: =+J63/D63 -> 0.25 | M63: =+G63+J63 -> 303.835 | N63: =M63*E63 -> 525.63455 | O63: =+M63/D63 -> 0.75000617 | P63: =+D63-M63 -> 101.275 | Q63: =P63*E63 -> 175.20575 | R63: =+P63/D63 -> 0.24999383 | S63: =N63+Q63 -> 700.8403 | T63: =F63-S63 -> -0.0003
A64: 2 | B64: ESTRUCTURAS | F64: =+F65+F129+F152+F176 -> 753983.13
A65: 02.01 | B65: CREMATORIO | F65: =+F66+F75+F81+F127 -> 187644.34
A66: 02.01.01 | B66: MOVIMIENTO DE TIERRAS | F66: =SUM(F67:F74) -> 18164.22 | S66: =N66+Q66 -> #VALUE! | T66: =F66-S66 -> #VALUE!
A67: 02.01.01.01 | B67: CORTE DE TERRENO PARA ADOQUINADO | C67: m3 | D67: 11.53 | E67: 18.72 | F67: =+ROUND((D67*E67),2) -> 215.84 | G67: 11.53 | H67: =G67*E67 -> 215.8416 | I67: =+G67/D67 -> 1 | K67: =J67*E67 -> 0 | L67: =+J67/D67 -> 0 | M67: =+G67+J67 -> 11.53 | N67: =M67*E67 -> 215.8416 | O67: =+M67/D67 -> 1 | P67: =+D67-M67 -> 0 | Q67: =P67*E67 -> 0 | R67: =+P67/D67 -> 0 | S67: =N67+Q67 -> 215.8416 | T67: =F67-S67 -> -0.0016
A68: 02.01.01.02 | B68: REFINE, NIVELACION Y COMPACTACION DE TERRENO NATURAL | C68: m2 | D68: 28.82 | E68: 6.28 | F68: =+ROUND((D68*E68),2) -> 180.99 | G68: 28.82 | H68: =G68*E68 -> 180.9896 | I68: =+G68/D68 -> 1 | K68: =J68*E68 -> 0 | L68: =+J68/D68 -> 0 | M68: =+G68+J68 -> 28.82 | N68: =M68*E68 -> 180.9896 | O68: =+M68/D68 -> 1 | P68: =+D68-M68 -> 0 | Q68: =P68*E68 -> 0 | R68: =+P68/D68 -> 0 | S68: =N68+Q68 -> 180.9896 | T68: =F68-S68 -> 0.0004
A69: 02.01.01.03 | B69: ACARREO INTERNO DE MATERIAL PROCEDENTE DEL CORTE (ADOQUINADO+CREMATORIO) | C69: m3 | D69: 122.48 | E69: 10.4 | F69: =+ROUND((D69*E69),2) -> 1273.79 | G69: 122.48 | H69: =G69*E69 -> 1273.792 | I69: =+G69/D69 -> 1 | K69: =J69*E69 -> 0 | L69: =+J69/D69 -> 0 | M69: =+G69+J69 -> 122.48 | N69: =M69*E69 -> 1273.792 | O69: =+M69/D69 -> 1 | P69: =+D69-M69 -> 0 | Q69: =P69*E69 -> 0 | R69: =+P69/D69 -> 0 | S69: =N69+Q69 -> 1273.792 | T69: =F69-S69 -> -0.002
A70: 02.01.01.04 | B70: ELIMINACION DE MATERIAL EXCEDENTE (ADOQUINADO+CREMATORIO) | C70: m3 | D70: 146.97 | E70: 31.34 | F70: =+ROUND((D70*E70),2) -> 4606.04 | G70: 146.97 | H70: =G70*E70 -> 4606.0398 | I70: =+G70/D70 -> 1 | K70: =J70*E70 -> 0 | L70: =+J70/D70 -> 0 | M70: =+G70+J70 -> 146.97 | N70: =M70*E70 -> 4606.0398 | O70: =+M70/D70 -> 1 | P70: =+D70-M70 -> 0 | Q70: =P70*E70 -> 0 | R70: =+P70/D70 -> 0 | S70: =N70+Q70 -> 4606.0398 | T70: =F70-S70 -> 0.0002
A71: 02.01.01.05 | B71: CORTE DE TERRENO PARA CREMATORIO | C71: m3 | D71: 55.8 | E71: 11.24 | F71: =+ROUND((D71*E71),2) -> 627.19 | G71: 55.8 | H71: =G71*E71 -> 627.192 | I71: =+G71/D71 -> 1 | K71: =J71*E71 -> 0 | L71: =+J71/D71 -> 0 | M71: =+G71+J71 -> 55.8 | N71: =M71*E71 -> 627.192 | O71: =+M71/D71 -> 1 | P71: =+D71-M71 -> 0 | Q71: =P71*E71 -> 0 | R71: =+P71/D71 -> 0 | S71: =N71+Q71 -> 627.192 | T71: =F71-S71 -> -0.002
A72: 02.01.01.06 | B72: REFINE, NIVELACION Y COMPACTACION DE TERRENO NATURAL | C72: m2 | D72: 139.5 | E72: 6.28 | F72: =+ROUND((D72*E72),2) -> 876.06 | G72: 139.5 | H72: =G72*E72 -> 876.06 | I72: =+G72/D72 -> 1 | K72: =J72*E72 -> 0 | L72: =+J72/D72 -> 0 | M72: =+G72+J72 -> 139.5 | N72: =M72*E72 -> 876.06 | O72: =+M72/D72 -> 1 | P72: =+D72-M72 -> 0 | Q72: =P72*E72 -> 0 | R72: =+P72/D72 -> 0 | S72: =N72+Q72 -> 876.06 | T72: =F72-S72 -> 0
A73: 02.01.01.07 | B73: EXCAVACION MANUAL EN TERRENO NORMAL | C73: m3 | D73: 55.15 | E73: 44.95 | F73: =+ROUND((D73*E73),2) -> 2478.99 | G73: 55.15 | H73: =G73*E73 -> 2478.9925 | I73: =+G73/D73 -> 1 | K73: =J73*E73 -> 0 | L73: =+J73/D73 -> 0 | M73: =+G73+J73 -> 55.15 | N73: =M73*E73 -> 2478.9925 | O73: =+M73/D73 -> 1 | P73: =+D73-M73 -> 0 | Q73: =P73*E73 -> 0 | R73: =+P73/D73 -> 0 | S73: =N73+Q73 -> 2478.9925 | T73: =F73-S73 -> -0.0025
A74: 02.01.01.08 | B74: RELLENO CON MATERIAL DE PRESTAMO (AFIRMADO) | C74: m3 | D74: 76.9 | E74: 102.8 | F74: =+ROUND((D74*E74),2) -> 7905.32 | G74: 76.9 | H74: =G74*E74 -> 7905.32 | I74: =+G74/D74 -> 1 | K74: =J74*E74 -> 0 | L74: =+J74/D74 -> 0 | M74: =+G74+J74 -> 76.9 | N74: =M74*E74 -> 7905.32 | O74: =+M74/D74 -> 1 | P74: =+D74-M74 -> 0 | Q74: =P74*E74 -> 0 | R74: =+P74/D74 -> 0 | S74: =N74+Q74 -> 7905.32 | T74: =F74-S74 -> 0
A75: 02.01.02 | B75: OBRAS DE CONCRETO SIMPLE | F75: =SUM(F76:F80) -> 23281.7 | S75: =N75+Q75 -> #VALUE! | T75: =F75-S75 -> #VALUE!
A76: 02.01.02.01 | B76: SOLADO e=4" (ZAPATAS) | C76: m2 | D76: 29.4 | E76: 31.27 | F76: =+ROUND((D76*E76),2) -> 919.34 | G76: 29.4 | H76: =G76*E76 -> 919.338 | I76: =+G76/D76 -> 1 | K76: =J76*E76 -> 0 | L76: =+J76/D76 -> 0 | M76: =+G76+J76 -> 29.4 | N76: =M76*E76 -> 919.338 | O76: =+M76/D76 -> 1 | P76: =+D76-M76 -> 0 | Q76: =P76*E76 -> 0 | R76: =+P76/D76 -> 0 | S76: =N76+Q76 -> 919.338 | T76: =F76-S76 -> 0.002
A77: 02.01.02.02 | B77: CIMIENTO CORRIDO f'c=175 kg/cm2 + 30% P.M. | C77: m3 | D77: 17.53 | E77: 301.67 | F77: =+ROUND((D77*E77),2) -> 5288.28 | G77: 17.53 | H77: =G77*E77 -> 5288.2751 | I77: =+G77/D77 -> 1 | K77: =J77*E77 -> 0 | L77: =+J77/D77 -> 0 | M77: =+G77+J77 -> 17.53 | N77: =M77*E77 -> 5288.2751 | O77: =+M77/D77 -> 1 | P77: =+D77-M77 -> 0 | Q77: =P77*E77 -> 0 | R77: =+P77/D77 -> 0 | S77: =N77+Q77 -> 5288.2751 | T77: =F77-S77 -> 0.0049
A78: 02.01.02.03 | B78: SOBRECIMIENTO f'c=175 kg/cm2 + 30% P.M. | C78: m3 | D78: 9.98 | E78: 345.25 | F78: =+ROUND((D78*E78),2) -> 3445.6 | G78: 9.98 | H78: =G78*E78 -> 3445.595 | I78: =+G78/D78 -> 1 | K78: =J78*E78 -> 0 | L78: =+J78/D78 -> 0 | M78: =+G78+J78 -> 9.98 | N78: =M78*E78 -> 3445.595 | O78: =+M78/D78 -> 1 | P78: =+D78-M78 -> 0 | Q78: =P78*E78 -> 0 | R78: =+P78/D78 -> 0 | S78: =N78+Q78 -> 3445.595 | T78: =F78-S78 -> 0.005
A79: 02.01.02.04 | B79: ENCOFRADO Y DESENCOFRADO DE SOBRECIMIENTO | C79: m2 | D79: 133.08 | E79: 67.21 | F79: =+ROUND((D79*E79),2) -> 8944.31 | G79: 133.08 | H79: =G79*E79 -> 8944.3068 | I79: =+G79/D79 -> 1 | K79: =J79*E79 -> 0 | L79: =+J79/D79 -> 0 | M79: =+G79+J79 -> 133.08 | N79: =M79*E79 -> 8944.3068 | O79: =+M79/D79 -> 1 | P79: =+D79-M79 -> 0 | Q79: =P79*E79 -> 0 | R79: =+P79/D79 -> 0 | S79: =N79+Q79 -> 8944.3068 | T79: =F79-S79 -> 0.0032
A80: 02.01.02.05 | B80: CONCRETO FALSO PISO MEZCLA 1:8 CEMENTO-HORMIGON e=4" | C80: m2 | D80: 121.73 | E80: 38.48 | F80: =+ROUND((D80*E80),2) -> 4684.17 | G80: 0 | H80: =G80*E80 -> 0 | I80: =+G80/D80 -> 0 | J80: =+D80 -> 121.73 | K80: =J80*E80 -> 4684.1704 | L80: =+J80/D80 -> 1 | M80: =+G80+J80 -> 121.73 | N80: =M80*E80 -> 4684.1704 | O80: =+M80/D80 -> 1 | P80: =+D80-M80 -> 0 | Q80: =P80*E80 -> 0 | R80: =+P80/D80 -> 0 | S80: =N80+Q80 -> 4684.1704 | T80: =F80-S80 -> -0.0004
A81: 02.01.03 | B81: OBRAS DE CONCRETO ARMADO | F81: =+F82+F86+F91+F96+F101+F106+F112+F117+F122 -> 145644.02 | S81: =N81+Q81 -> #VALUE! | T81: =F81-S81 -> #VALUE!
A82: 02.01.03.01 | B82: ZAPATAS AISLADAS | F82: =SUM(F83:F85) -> 18790.43 | S82: =N82+Q82 -> #VALUE! | T82: =F82-S82 -> #VALUE!
A83: 02.01.03.01.01 | B83: CONCRETO f'c=210 kg/cm2 - ZAPATAS | C83: m3 | D83: 17.33 | E83: 388.22 | F83: =+ROUND((D83*E83),2) -> 6727.85 | G83: 17.33 | H83: =G83*E83 -> 6727.8526 | I83: =+G83/D83 -> 1 | K83: =J83*E83 -> 0 | L83: =+J83/D83 -> 0 | M83: =+G83+J83 -> 17.33 | N83: =M83*E83 -> 6727.8526 | O83: =+M83/D83 -> 1 | P83: =+D83-M83 -> 0 | Q83: =P83*E83 -> 0 | R83: =+P83/D83 -> 0 | S83: =N83+Q83 -> 6727.8526 | T83: =F83-S83 -> -0.0026
A84: 02.01.03.01.02 | B84: ACERO DE REFUERZO fy=4,200 kg/cm2 | C84: kg | D84: 1529.4 | E84: 7.82 | F84: =+ROUND((D84*E84),2) -> 11959.91 | G84: 1529.4 | H84: =G84*E84 -> 11959.908 | I84: =+G84/D84 -> 1 | K84: =J84*E84 -> 0 | L84: =+J84/D84 -> 0 | M84: =+G84+J84 -> 1529.4 | N84: =M84*E84 -> 11959.908 | O84: =+M84/D84 -> 1 | P84: =+D84-M84 -> 0 | Q84: =P84*E84 -> 0 | R84: =+P84/D84 -> 0 | S84: =N84+Q84 -> 11959.908 | T84: =F84-S84 -> 0.002
A85: 02.01.03.01.03 | B85: CURADO DE CONCRETO | C85: m2 | D85: 48.89 | E85: 2.1 | F85: =+ROUND((D85*E85),2) -> 102.67 | G85: 48.89 | H85: =G85*E85 -> 102.669 | I85: =+G85/D85 -> 1 | K85: =J85*E85 -> 0 | L85: =+J85/D85 -> 0 | M85: =+G85+J85 -> 48.89 | N85: =M85*E85 -> 102.669 | O85: =+M85/D85 -> 1 | P85: =+D85-M85 -> 0 | Q85: =P85*E85 -> 0 | R85: =+P85/D85 -> 0 | S85: =N85+Q85 -> 102.669 | T85: =F85-S85 -> 0.001
A86: 02.01.03.02 | B86: COLUMNAS | F86: =SUM(F87:F90) -> 32651.49 | S86: =N86+Q86 -> #VALUE! | T86: =F86-S86 -> #VALUE!
A87: 02.01.03.02.01 | B87: CONCRETO f'c=210 kg/cm2 - COLUMNAS | C87: m3 | D87: 11.05 | E87: 578.63 | F87: =+ROUND((D87*E87),2) -> 6393.86 | G87: 11.05 | H87: =G87*E87 -> 6393.8615 | I87: =+G87/D87 -> 1 | K87: =J87*E87 -> 0 | L87: =+J87/D87 -> 0 | M87: =+G87+J87 -> 11.05 | N87: =M87*E87 -> 6393.8615 | O87: =+M87/D87 -> 1 | P87: =+D87-M87 -> 0 | Q87: =P87*E87 -> 0 | R87: =+P87/D87 -> 0 | S87: =N87+Q87 -> 6393.8615 | T87: =F87-S87 -> -0.0015
A88: 02.01.03.02.02 | B88: ENCOFRADO Y DESENCOFRADO DE COLUMNAS | C88: m2 | D88: 142.26 | E88: 78.77 | F88: =+ROUND((D88*E88),2) -> 11205.82 | G88: 142.26 | H88: =G88*E88 -> 11205.82 | I88: =+G88/D88 -> 1 | K88: =J88*E88 -> 0 | L88: =+J88/D88 -> 0 | M88: =+G88+J88 -> 142.26 | N88: =M88*E88 -> 11205.82 | O88: =+M88/D88 -> 1 | P88: =+D88-M88 -> 0 | Q88: =P88*E88 -> 0 | R88: =+P88/D88 -> 0 | S88: =N88+Q88 -> 11205.82 | T88: =F88-S88 -> -0.0002
A89: 02.01.03.02.03 | B89: ACERO DE REFUERZO fy=4,200 kg/cm2 | C89: kg | D89: 1886.58 | E89: 7.82 | F89: =+ROUND((D89*E89),2) -> 14753.06 | G89: 1886.58 | H89: =G89*E89 -> 14753.056 | I89: =+G89/D89 -> 1 | K89: =J89*E89 -> 0 | L89: =+J89/D89 -> 0 | M89: =+G89+J89 -> 1886.58 | N89: =M89*E89 -> 14753.056 | O89: =+M89/D89 -> 1 | P89: =+D89-M89 -> 0 | Q89: =P89*E89 -> 0 | R89: =+P89/D89 -> 0 | S89: =N89+Q89 -> 14753.056 | T89: =F89-S89 -> 0.0044
A90: 02.01.03.02.04 | B90: CURADO DE CONCRETO | C90: m2 | D90: 142.26 | E90: 2.1 | F90: =+ROUND((D90*E90),2) -> 298.75 | G90: 142.26 | H90: =G90*E90 -> 298.746 | I90: =+G90/D90 -> 1 | K90: =J90*E90 -> 0 | L90: =+J90/D90 -> 0 | M90: =+G90+J90 -> 142.26 | N90: =M90*E90 -> 298.746 | O90: =+M90/D90 -> 1 | P90: =+D90-M90 -> 0 | Q90: =P90*E90 -> 0 | R90: =+P90/D90 -> 0 | S90: =N90+Q90 -> 298.746 | T90: =F90-S90 -> 0.004
A91: 02.01.03.03 | B91: COLUMNETAS | F91: =SUM(F92:F95) -> 2622.48 | S91: =N91+Q91 -> #VALUE! | T91: =F91-S91 -> #VALUE!
A92: 02.01.03.03.01 | B92: CONCRETO f'c=210 kg/cm2 - COLUMNETAS | C92: m3 | D92: 1.07 | E92: 375.62 | F92: =+ROUND((D92*E92),2) -> 401.91 | G92: 1.07 | H92: =G92*E92 -> 401.9134 | I92: =+G92/D92 -> 1 | K92: =J92*E92 -> 0 | L92: =+J92/D92 -> 0 | M92: =+G92+J92 -> 1.07 | N92: =M92*E92 -> 401.9134 | O92: =+M92/D92 -> 1 | P92: =+D92-M92 -> 0 | Q92: =P92*E92 -> 0 | R92: =+P92/D92 -> 0 | S92: =N92+Q92 -> 401.9134 | T92: =F92-S92 -> -0.0034
A93: 02.01.03.03.02 | B93: ENCOFRADO Y DESENCOFRADO DE COLUMNETAS | C93: m2 | D93: 22.8 | E93: 59.87 | F93: =+ROUND((D93*E93),2) -> 1365.04 | G93: 22.8 | H93: =G93*E93 -> 1365.036 | I93: =+G93/D93 -> 1 | K93: =J93*E93 -> 0 | L93: =+J93/D93 -> 0 | M93: =+G93+J93 -> 22.8 | N93: =M93*E93 -> 1365.036 | O93: =+M93/D93 -> 1 | P93: =+D93-M93 -> 0 | Q93: =P93*E93 -> 0 | R93: =+P93/D93 -> 0 | S93: =N93+Q93 -> 1365.036 | T93: =F93-S93 -> 0.004
A94: 02.01.03.03.03 | B94: ACERO DE REFUERZO fy=4,200 kg/cm2 | C94: kg | D94: 103.28 | E94: 7.82 | F94: =+ROUND((D94*E94),2) -> 807.65 | G94: 103.28 | H94: =G94*E94 -> 807.6496 | I94: =+G94/D94 -> 1 | K94: =J94*E94 -> 0 | L94: =+J94/D94 -> 0 | M94: =+G94+J94 -> 103.28 | N94: =M94*E94 -> 807.6496 | O94: =+M94/D94 -> 1 | P94: =+D94-M94 -> 0 | Q94: =P94*E94 -> 0 | R94: =+P94/D94 -> 0 | S94: =N94+Q94 -> 807.6496 | T94: =F94-S94 -> 0.0004
A95: 02.01.03.03.04 | B95: CURADO DE CONCRETO | C95: m2 | D95: 22.8 | E95: 2.1 | F95: =+ROUND((D95*E95),2) -> 47.88 | G95: 22.8 | H95: =G95*E95 -> 47.88 | I95: =+G95/D95 -> 1 | K95: =J95*E95 -> 0 | L95: =+J95/D95 -> 0 | M95: =+G95+J95 -> 22.8 | N95: =M95*E95 -> 47.88 | O95: =+M95/D95 -> 1 | P95: =+D95-M95 -> 0 | Q95: =P95*E95 -> 0 | R95: =+P95/D95 -> 0 | S95: =N95+Q95 -> 47.88 | T95: =F95-S95 -> 0
A96: 02.01.03.04 | B96: VIGAS ESTRUCTURALES | F96: =SUM(F97:F100) -> 17028.9
A97: 02.01.03.04.01 | B97: CONCRETO f'c=210 kg/cm2 - VIGAS ESTRUCTURALES | C97: m3 | D97: 8.25 | E97: 438.14 | F97: =+ROUND((D97*E97),2) -> 3614.66 | G97: 8.25 | H97: =G97*E97 -> 3614.655 | I97: =+G97/D97 -> 1 | K97: =J97*E97 -> 0 | L97: =+J97/D97 -> 0 | M97: =+G97+J97 -> 8.25 | N97: =M97*E97 -> 3614.655 | O97: =+M97/D97 -> 1 | P97: =+D97-M97 -> 0 | Q97: =P97*E97 -> 0 | R97: =+P97/D97 -> 0 | S97: =N97+Q97 -> 3614.655 | T97: =F97-S97 -> 0.005
A98: 02.01.03.04.02 | B98: ENCOFRADO Y DESENCOFRADO DE VIGAS ESTRUCTURALES | C98: m2 | D98: 50.1 | E98: 85.51 | F98: =+ROUND((D98*E98),2) -> 4284.05 | G98: 50.1 | H98: =G98*E98 -> 4284.051 | I98: =+G98/D98 -> 1 | K98: =J98*E98 -> 0 | L98: =+J98/D98 -> 0 | M98: =+G98+J98 -> 50.1 | N98: =M98*E98 -> 4284.051 | O98: =+M98/D98 -> 1 | P98: =+D98-M98 -> 0 | Q98: =P98*E98 -> 0 | R98: =+P98/D98 -> 0 | S98: =N98+Q98 -> 4284.051 | T98: =F98-S98 -> -0.001
A99: 02.01.03.04.03 | B99: ACERO DE REFUERZO fy=4,200 kg/cm2 | C99: kg | D99: 1154.09 | E99: 7.82 | F99: =+ROUND((D99*E99),2) -> 9024.98 | G99: 1154.09 | H99: =G99*E99 -> 9024.9838 | I99: =+G99/D99 -> 1 | K99: =J99*E99 -> 0 | L99: =+J99/D99 -> 0 | M99: =+G99+J99 -> 1154.09 | N99: =M99*E99 -> 9024.9838 | O99: =+M99/D99 -> 1 | P99: =+D99-M99 -> 0 | Q99: =P99*E99 -> 0 | R99: =+P99/D99 -> 0 | S99: =N99+Q99 -> 9024.9838 | T99: =F99-S99 -> -0.0038
A100: 02.01.03.04.04 | B100: CURADO DE CONCRETO | C100: m2 | D100: 50.1 | E100: 2.1 | F100: =+ROUND((D100*E100),2) -> 105.21 | G100: 50.1 | H100: =G100*E100 -> 105.21 | I100: =+G100/D100 -> 1 | K100: =J100*E100 -> 0 | L100: =+J100/D100 -> 0 | M100: =+G100+J100 -> 50.1 | N100: =M100*E100 -> 105.21 | O100: =+M100/D100 -> 1 | P100: =+D100-M100 -> 0 | Q100: =P100*E100 -> 0 | R100: =+P100/D100 -> 0 | S100: =N100+Q100 -> 105.21 | T100: =F100-S100 -> 0
A101: 02.01.03.05 | B101: VIGAS DE CONFINAMIENTO | F101: =SUM(F102:F105) -> 9759.33 | S101: =N101+Q101 -> #VALUE! | T101: =F101-S101 -> #VALUE!
A102: 02.01.03.05.01 | B102: CONCRETO f'c=210 kg/cm2 - VIGUETAS | C102: m3 | D102: 4.59 | E102: 409.25 | F102: =+ROUND((D102*E102),2) -> 1878.46 | G102: 4.59 | H102: =G102*E102 -> 1878.4575 | I102: =+G102/D102 -> 1 | K102: =J102*E102 -> 0 | L102: =+J102/D102 -> 0 | M102: =+G102+J102 -> 4.59 | N102: =M102*E102 -> 1878.4575 | O102: =+M102/D102 -> 1 | P102: =+D102-M102 -> 0 | Q102: =P102*E102 -> 0 | R102: =+P102/D102 -> 0 | S102: =N102+Q102 -> 1878.4575 | T102: =F102-S102 -> 0.0025
A103: 02.01.03.05.02 | B103: ENCOFRADO Y DESENCOFRADO DE VIGUETAS | C103: m2 | D103: 63.16 | E103: 87.88 | F103: =+ROUND((D103*E103),2) -> 5550.5 | G103: 63.16 | H103: =G103*E103 -> 5550.5008 | I103: =+G103/D103 -> 1 | K103: =J103*E103 -> 0 | L103: =+J103/D103 -> 0 | M103: =+G103+J103 -> 63.16 | N103: =M103*E103 -> 5550.5008 | O103: =+M103/D103 -> 1 | P103: =+D103-M103 -> 0 | Q103: =P103*E103 -> 0 | R103: =+P103/D103 -> 0 | S103: =N103+Q103 -> 5550.5008 | T103: =F103-S103 -> -0.0008
A104: 02.01.03.05.03 | B104: ACERO DE REFUERZO fy=4,200 kg/cm2 | C104: kg | D104: 281.04 | E104: 7.82 | F104: =+ROUND((D104*E104),2) -> 2197.73 | G104: 281.04 | H104: =G104*E104 -> 2197.7328 | I104: =+G104/D104 -> 1 | K104: =J104*E104 -> 0 | L104: =+J104/D104 -> 0 | M104: =+G104+J104 -> 281.04 | N104: =M104*E104 -> 2197.7328 | O104: =+M104/D104 -> 1 | P104: =+D104-M104 -> 0 | Q104: =P104*E104 -> 0 | R104: =+P104/D104 -> 0 | S104: =N104+Q104 -> 2197.7328 | T104: =F104-S104 -> -0.0028
A105: 02.01.03.05.04 | B105: CURADO DE CONCRETO | C105: m2 | D105: 63.16 | E105: 2.1 | F105: =+ROUND((D105*E105),2) -> 132.64 | G105: 63.16 | H105: =G105*E105 -> 132.636 | I105: =+G105/D105 -> 1 | K105: =J105*E105 -> 0 | L105: =+J105/D105 -> 0 | M105: =+G105+J105 -> 63.16 | N105: =M105*E105 -> 132.636 | O105: =+M105/D105 -> 1 | P105: =+D105-M105 -> 0 | Q105: =P105*E105 -> 0 | R105: =+P105/D105 -> 0 | S105: =N105+Q105 -> 132.636 | T105: =F105-S105 -> 0.004
A106: 02.01.03.06 | B106: LOSA ALIGERADA | F106: =SUM(F107:F111) -> 14341.89 | S106: =N106+Q106 -> #VALUE! | T106: =F106-S106 -> #VALUE!
...

Sheet SUSTENTO METRADOS
B2: VALORIZACIÓN N° 02 (PERIODO 01 AL 30 DE NOVIEMBRE 2025)
B3: CONTRATISTA | C3: =+[17]FICHA!E4 -> "CONSTRUCCION DE NICHO, COLUMBARIO Y CREMATORIO; REMODELACION DE VELATORIO; EN EL (LA) CEMENTERIO MUNICIPAL EN EL CENTRO POBLADO SANTIAGO DE SURCO, DISTRITO DE SANTIAGO DE SURCO, PROVINCIA LIMA, DEPARTAMENTO LIMA" CUI N| 2658565 - ETAPA COLUMBARIO.
B4: CONTRATISTA | C4: =+[17]FICHA!E9 -> CONSORCIO LIMA
B5: ENTIDAD | C5: MUNICIPALIDAD DISTRITAL DE SANTIAGO DE SURCO
B6: RESIDENTE | C6: =+[17]FICHA!E11 -> ING. GUIDO JAVIER VALVERDE TRUJILLO
B7: SUPERVISOR | C7: =+[17]FICHA!E10 -> ING. JOSE ISMAEL MOSCOSO PINGO
B8: SUSTENTO DE METRADOS EJECUTADOS DURANTE EL PERIODO
B9: ITEM | C9: DESCRIPCION | D9: UND | E9: LARGO | F9: ANCHO | G9: ALTURA | H9: Nº DE VECES | I9: PARCIAL | J9: TOTAL
B10: 01.01.02 | C10: INSTALACIONES PROVISIONALES
B11: 01.01.02.01 | C11: ALQUILER DE BAÑOS QUIMICOS PORTATILES | D11: mes | J11: 1
B12: 01.01.02.04 | C12: AGUA PROVISIONAL PARA LA CONSTRUCCION | D12: mes | J12: 1
B13: 01.01.02.05 | C13: ENERGIA ELECTRICA PROVISIONAL | D13: mes | J13: 1
B14: 01.02.02 | C14: VELATORIO
B15: 01.02.02.01 | C15: DEMOLICIÓN DE MUROS EXISTENTES | D15: m2 | H15: área = | I15: 30.39 | J15: 30.39
B16: 01.02.02.02 | C16: DESMONTAJE DE APARATOS SANITARIOS EXISTENTES EN LA OFICINA DE ADMINISTRACIÓN | D16: glb | J16: 1
B17: 01.02.02.03 | C17: RETIRO DE CERÁMICO EXISTENTE EN LA OFICINA | D17: m2 | H17: área = | I17: =+J17 -> 54.65 | J17: 54.65
B18: 01.02.02.04 | C18: RETIRO DE PISO EXISTENTE EN NUEVA ZONA DE KITCHENETTE Y CANALETAS | D18: m2 | H18: área = | I18: =+J18 -> 3.46 | J18: 3.46
B19: 01.02.02.05 | C19: DESMONTAJE DE SISTEMAS ELECTRICOS, INC. SELLADO DE SALIDAS SEGÚN PLANO | D19: glb | J19: 1
B20: 01.02.02.06 | C20: DESMONTAJE DE SISTEMAS DE COMUNICACIONES Y REDES | D20: glb | J20: 1
B21: 01.02.02.07 | C21: ELIMINACION DE MATERIAL EXCEDENTE C/VOLQ. 15M3, D=10km | D21: m3 | H21: vol = | I21: =+J21 -> 12.64 | J21: 12.64
B22: 1.03 | C22: SEGURIDAD Y SALUD EN EL TRABAJO
B23: 01.03.02 | C23: EQUIPOS DE PROTECCION INDIVIDUAL | D23: glb | J23: 0.25
B24: 01.03.03 | C24: EQUIPOS DE PROTECCION COLECTIVA | D24: glb | J24: 0.25
B25: 01.03.04 | C25: SEÑALIZACIÓN TEMPORAL DE SEGURIDAD | D25: glb | J25: 0.25
B26: 01.03.05 | C26: CAPACITACION EN SEGURIDAD Y SALUD | D26: glb | J26: 0.25
B27: 01.03.06 | C27: RECURSOS PARA RESPUESTAS ANTE EMERGENCIAS | D27: glb | J27: 0.25
B28: 01.04 | C28: PLAN DE MANEJO AMBIENTAL
B29: 01.04.04 | C29: PROGRAMA DE USO DE AGUA | D29: glb | J29: 0.5
B30: 01.04.05 | C30: PROGRAMA DE EDUCACION, FORMACION Y CAPACITACION DE PERSONAL | D30: glb | J30: 0.5
B31: 01.04.06 | C31: PROGRAMA DE SEGURIDAD Y SALUD OCUPACIONAL | D31: glb | J31: 0.5
B32: 01.04.07 | C32: PLAN DE CONTINGENCIAS | D32: glb | J32: 0.5
B33: 01.05 | C33: TRAZO Y REPLANTEO
B34: 01.05.02 | C34: TRAZO NIVELACION Y REPLANTEO DURANTE EL PROCESO | D34: m2 | H34: área = | I34: =+J34 -> 101.28 | J34: 101.28
B35: 2 | C35: ESTRUCTURAS
B36: 02.01 | C36: CREMATORIO
B37: 02.01.01 | C37: MOVIMIENTO DE TIERRAS
B38: 02.01.01.08 | C38: RELLENO CON MATERIAL DE PRESTAMO (AFIRMADO) | D38: m3 | H38: vol = | I38: =+J38 -> 76.9 | J38: 76.9
B39: 02.01.02 | C39: OBRAS DE CONCRETO SIMPLE
B40: 02.01.02.02 | C40: CIMIENTO CORRIDO f'c=175 kg/cm2 + 30% P.M. | D40: m3 | H40: vol = | I40: =+J40 -> 17.53 | J40: 17.53
B41: 02.01.02.03 | C41: SOBRECIMIENTO f'c=175 kg/cm2 + 30% P.M. | D41: m3 | H41: vol = | I41: =+J41 -> 9.98 | J41: 9.98
B42: 02.01.02.04 | C42: ENCOFRADO Y DESENCOFRADO DE SOBRECIMIENTO | D42: m2 | H42: área = | I42: =+J42 -> 133.08 | J42: 133.08
B43: 02.01.03.02 | C43: COLUMNAS
B44: 02.01.03.02.01 | C44: CONCRETO f'c=210 kg/cm2 - COLUMNAS | D44: m3 | H44: vol = | I44: =+J44 -> 11.05 | J44: 11.05
C45: COLUMNA C-01 | E45: 0.25 | F45: 0.5 | G45: 5.75 | H45: 8 | I45: =PRODUCT(E45:H45) -> 5.75
C46: COLUMNA C-02 | E46: 0.25 | F46: 0.4 | G46: 5.75 | H46: 4 | I46: =PRODUCT(E46:H46) -> 2.3
C47: COLUMNA C-03 | E47: 0.25 | F47: 0.3 | G47: 5.75 | H47: 1 | I47: =PRODUCT(E47:H47) -> 0.43125
C48: COLUMNA C-04 | E48: 0.16 | G48: 5.75 | H48: 1 | I48: =PRODUCT(E48:H48) -> 0.92
C49: PLACA PL-1 | E49: 1.15 | F49: 0.25 | G49: 5.75 | H49: 1 | I49: =PRODUCT(E49:H49) -> 1.653125
B50: 02.01.03.02.02 | C50: ENCOFRADO Y DESENCOFRADO DE COLUMNAS | D50: m2 | H50: área = | I50: =+J50 -> 142.26 | J50: 142.26
C51: COLUMNA C-01 | E51: 0.25 | G51: 5.75 | H51: 16 | I51: =PRODUCT(E51:H51) -> 23
F52: 0.5 | G52: 5.75 | H52: 16 | I52: =PRODUCT(E52:H52) -> 46
C53: COLUMNA C-02 | E53: 0.25 | G53: 5.75 | H53: 8 | I53: =PRODUCT(E53:H53) -> 11.5
F54: 0.4 | G54: 5.75 | H54: 8 | I54: =PRODUCT(E54:H54) -> 18.4
C55: COLUMNA C-03 | E55: 0.25 | G55: 5.75 | H55: 2 | I55: =PRODUCT(E55:H55) -> 2.875
F56: 0.3 | G56: 5.75 | H56: 2 | I56: =PRODUCT(E56:H56) -> 3.45
C57: COLUMNA C-04 | E57: 1.82 | G57: 5.75 | H57: 2 | I57: =PRODUCT(E57:H57) -> 20.93
C58: PLACA PL-1 | E58: 1.15 | G58: 5.75 | H58: 2 | I58: =PRODUCT(E58:H58) -> 13.225
F59: 0.25 | G59: 5.75 | H59: 2 | I59: =PRODUCT(E59:H59) -> 2.875
B60: 02.01.03.02.04 | C60: CURADO DE CONCRETO | D60: m2 | H60: área = | I60: =+J60 -> 142.26 | J60: 142.26
B61: 02.01.03.03 | C61: COLUMNETAS
B62: 02.01.03.03.01 | C62: CONCRETO f'c=210 kg/cm2 - COLUMNETAS | D62: m3 | J62: 1.07
B63: 02.01.03.03.02 | C63: ENCOFRADO Y DESENCOFRADO DE COLUMNETAS | D63: m2 | J63: 22.8
B64: 02.01.03.03.03 | C64: ACERO DE REFUERZO fy=4,200 kg/cm2 | D64: kg | J64: 103.28
B65: 02.01.03.03.04 | C65: CURADO DE CONCRETO | D65: m2 | J65: 22.8
B66: 02.01.03.04 | C66: VIGAS ESTRUCTURALES
B67: 02.01.03.04.01 | C67: CONCRETO f'c=210 kg/cm2 - VIGAS ESTRUCTURALES | D67: m3 | J67: 8.25
C68: VP-01 A4 | E68: 2.3 | F68: 0.25 | G68: 0.4 | H68: 1 | I68: =PRODUCT(E68:H68) -> 0.23
C69: VP-01 eje 4 entre a-b | E69: 4.67 | F69: 0.25 | G69: 0.4 | H69: 1 | I69: =PRODUCT(E69:H69) -> 0.467
C70: VP-01 eje 4 entre b-c | E70: 3.2 | F70: 0.25 | G70: 0.4 | H70: 1 | I70: =PRODUCT(E70:H70) -> 0.32
C71: VP-01 eje 4 entre c-d | E71: 5.03 | F71: 0.25 | G71: 0.4 | H71: 1 | I71: =PRODUCT(E71:H71) -> 0.503
C72: VP-01 eje 4 entre d-e | E72: 5.24 | F72: 0.25 | G72: 0.4 | H72: 1 | I72: =PRODUCT(E72:H72) -> 0.524
C73: VP-02 eje 2 entre a-b | E73: 4.1 | F73: 0.25 | G73: 0.4 | H73: 1 | I73: =PRODUCT(E73:H73) -> 0.41
C74: VP-02 eje 2 entre b-c | E74: 3 | F74: 0.25 | G74: 0.4 | H74: 1 | I74: =PRODUCT(E74:H74) -> 0.3
C75: VP-03 eje 1 entre a-b | E75: 4.1 | F75: 0.25 | G75: 0.4 | H75: 1 | I75: =PRODUCT(E75:H75) -> 0.41
C76: VP-03 eje 1 entre b-c | E76: 2.85 | F76: 0.25 | G76: 0.4 | H76: 1 | I76: =PRODUCT(E76:H76) -> 0.285
C77: VP-03 eje 1 entre c-d | E77: 4.5 | F77: 0.25 | G77: 0.4 | H77: 1 | I77: =PRODUCT(E77:H77) -> 0.45
C78: VP-03 eje 1 entre d-e | E78: 4.65 | F78: 0.25 | G78: 0.4 | H78: 1 | I78: =PRODUCT(E78:H78) -> 0.465
C79: VP-04 eje a entre 1-2 | E79: 3.09 | F79: 0.25 | G79: 0.4 | H79: 1 | I79: =PRODUCT(E79:H79) -> 0.309
... C89: Va | E89: 1 | F89: 0.15 | G89: 0.2 | H89: 2 | I89: =PRODUCT(E89:H89) -> 0.06
B90: 02.01.03.04.02 | C90: ENCOFRADO Y DESENCOFRADO DE VIGAS ESTRUCTURALES | D90: m2 | J90: 50.1
C91: VP-01 A4 | E91: 2.3 | G91: 0.4 | H91: 2 | I91: =PRODUCT(E91:H91) -> 1.84
C92: VP-01 eje 4 entre a-b | E92: 1 | G92: 0.7 | H92: 1 | I92: =PRODUCT(E92:H92) -> 0.7
C93: VP-01 eje 4 entre b-c | E93: 1 | G93: 0.7 | H93: 1 | I93: =PRODUCT(E93:H93) -> 0.7
C94: VP-01 eje 4 entre c-d | E94: 1 | G94: 0.7 | H94: 1 | I94: =PRODUCT(E94:H94) -> 0.7
C95: VP-01 eje 4 entre d-e | E95: 1 | G95: 0.7 | H95: 1 | I95: =PRODUCT(E95:H95) -> 0.7
C96: VP-02 eje 2 entre a-b | E96: 1 | G96: 0.55 | H96: 1 | I96: =PRODUCT(E96:H96) -> 0.55
C97: VP-02 eje 2 entre b-c | E97: 1 | G97: 0.55 | H97: 1 | I97: =PRODUCT(E97:H97) -> 0.55
C98: VP-03 eje 1 entre a-b | E98: 1 | G98: 0.7 | H98: 1 | I98: =PRODUCT(E98:H98) -> 0.7
C99: VP-03 eje 1 entre b-c | E99: 1 | G99: 0.7 | H99: 1 | I99: =PRODUCT(E99:H99) -> 0.7
C100: VP-03 eje 1 entre c-d | E100: 1 | G100: 0.7 | H100: 1 | I100: =PRODUCT(E100:H100) -> 0.7
C101: VP-03 eje 1 entre d-e | E101: 1 | G101: 0.55 | H101: 1 | I101: =PRODUCT(E101:H101) -> 0.55
C102: VP-04 eje a entre 1-2 | E102: 1 | G102: 0.8 | H102: 1 | I102: =PRODUCT(E102:H102) -> 0.8
... C109: VP-07 | E109: 1 | G109: 0.65 | H109: 1 | I109: =PRODUCT(E109:H109) -> 0.65
B110: 02.01.03.04.03 | C110: ACERO DE REFUERZO fy=4,200 kg/cm2 | D110: kg | J110: 1154.09
B111: 02.01.03.04.04 | C111: CURADO DE CONCRETO | D111: m2 | J111: 50.1
B112: 02.01.03.05 | C112: VIGAS DE CONFINAMIENTO
B113: 02.01.03.05.01 | C113: CONCRETO f'c=210 kg/cm2 - VIGUETAS | D113: m3 | J113: 4.59
C114: VP-01 A4 | E114: 2.3 | F114: 0.15 | G114: 0.4 | H114: 1 | I114: =PRODUCT(E114:H114) -> 0.138
C115: VP-01 eje 4 entre a-b | E115: 4.667 | F115: 0.15 | G115: 0.4 | H115: 1 | I115: =PRODUCT(E115:H115) -> 0.28002
C116: VP-01 eje 4 entre b-c | E116: 3.2 | F116: 0.15 | G116: 0.4 | H116: 1 | I116: =PRODUCT(E116:H116) -> 0.192
...

Sheet RES. MET. EJEC.
B2: VALORIZACIÓN N° 0 (PERIODO 01 AL 30 DE NOVIEMBRE 2025)
B3: CONTRATISTA | C3: =+FICHA!E4 -> "CONSTRUCCION DE NICHO, COLUMBARIO Y CREMATORIO; REMODELACION DE VELATORIO; EN EL (LA) CEMENTERIO MUNICIPAL EN EL CENTRO POBLADO SANTIAGO DE SURCO, DISTRITO DE SANTIAGO DE SURCO, PROVINCIA LIMA, DEPARTAMENTO LIMA" CUI N| 2658565 - ETAPA COLUMBARIO.
B4: CONTRATISTA | C4: =+FICHA!E9 -> CONSORCIO LIMA
B5: ENTIDAD | C5: MUNICIPALIDAD DISTRITAL DE SANTIAGO DE SURCO
B6: RESIDENTE | C6: =+FICHA!E11 -> ING. GUIDO JAVIER VALVERDE TRUJILLO
B7: SUPERVISOR | C7: =+FICHA!E10 -> ING. JOSE ISMAEL MOSCOSO PINGO
B8: RESUMEN DE METRADOS
B9: ITEM | C9: PARTIDA | D9: UND | H9: METRADO ACTUAL
B14: 01 | C14: OBRAS PROVISIONALES, TRABAJOS PRELIMINARES, SEGURIDAD Y SALUD
B15: 01.01 | C15: OBRAS PROVISIONALES | F15: 1804.51 | G15: =ROUND(E15*F15,2) -> 0 | I15: =+ROUND(H15*F15,2) -> 0
B16: 01.01.01 | C16: CONSTRUCCIONES PROVISIONALES | E16: 3 | F16: 1500 | G16: =ROUND(E16*F16,2) -> 4500 | I16: =+ROUND(H16*F16,2) -> 0
B17: 01.01.01.01 | C17: CARTEL DE IDENTIFICACION DE LA OBRA DE 3.60X2.40 m | D17: und | G17: =SUM(G18:G27) -> 4500 | J17: 1
B18: 01.01.01.02 | C18: CERCO PERIMETRICO PROVISIONAL DE MALLA RASCHELL H=2.10M | D18: m | E18: 1 | F18: 4500 | G18: =ROUND(E18*F18,2) -> 4500 | I18: =+ROUND(H18*F18,2) -> 0 | J18: 48.86
B19: 01.01.01.03 | C19: CERCO PERIMETRICO PROVISIONAL METALICO H=2.10M PROVISIONAL | D19: m | F19: 937.52 | G19: =ROUND(E19*F19,2) -> 0 | I19: =+ROUND(H19*F19,2) -> 0 | J19: 48.86
B20: 01.01.01.04 | C20: ALMACEN, OFICINA Y CASETA DE GUARDIANIA DE TRIPLAY | D20: m2 | J20: 26
B21: 01.01.01.05 | C21: TRANSPORTES DE MAQUINARIAS, EQUIPO Y HERRAMIENTAS A OBRA | D21: glb | J21: 1
B22: 01.01.01.06 | C22: TRANSPORTES DE MATERIALES | D22: glb | J22: 1
B23: 01.01.02 | C23: INSTALACIONES PROVISIONALES
B24: 01.01.02.01 | C24: ALQUILER DE BAÑOS QUIMICOS PORTATILES | D24: mes | J24: 1
B25: 01.01.02.02 | C25: SUM. E INST. PARA EL PUNTO DE AGUA EN OBRA | D25: glb | J25: 1
B26: 01.01.02.03 | C26: SUM. E INST. PARA EL PUNTO DE ENERGIA EN OBRA | D26: glb | J26: 1
B27: 01.01.02.04 | C27: AGUA PROVISIONAL PARA LA CONSTRUCCION | D27: mes | J27: 1
B28: 01.01.02.05 | C28: ENERGIA ELECTRICA PROVISIONAL | D28: mes | J28: 1
B29: 01.02 | C29: TRABAJOS PRELIMINARES
B30: 01.02.01 | C30: CREMATORIO
B31: 01.02.01.01 | C31: DESBROCE Y LIMPIEZA MANUAL DEL TERRENO | D31: m2 | J31: 163
B32: 01.02.01.02 | C32: ELIMINACION DE MALEZA Y ARBUSTOS DE FACIL EXTRACCION | D32: m3 | J32: 28.2
B33: 01.02.03 | C33: COLUMBARIO
B34: 01.02.03.01 | C34: DESBROCE Y LIMPIEZA MANUAL DEL TERRENO | D34: m2 | J34: 188.21
B35: 1.03 | C35: SEGURIDAD Y SALUD EN EL TRABAJO
B36: 01.03.01 | C36: ELABORACIÓN, IMPLEMENTACIÓN Y ADMINISTRACIÓN DEL PLAN DE SEGURIDAD Y SALUD EN EL TRABAJO | D36: glb | J36: 1
B37: 01.03.02 | C37: EQUIPOS DE PROTECCION INDIVIDUAL | D37: glb | J37: 0.25
B38: 01.03.03 | C38: EQUIPOS DE PROTECCION COLECTIVA | D38: glb | J38: 0.25
B39: 01.03.04 | C39: SEÑALIZACIÓN TEMPORAL DE SEGURIDAD | D39: glb | J39: 0.25
B40: 01.03.05 | C40: CAPACITACION EN SEGURIDAD Y SALUD | D40: glb | J40: 0.25
B41: 01.03.06 | C41: RECURSOS PARA RESPUESTAS ANTE EMERGENCIAS | D41: glb | J41: 0.25
B42: 01.04 | C42: PLAN DE MANEJO AMBIENTAL
B43: 01.04.01 | C43: PROGRAMA DE PREVENCION Y MITIGACION AMBIENTAL | D43: glb | J43: 1
B44: 01.05 | C44: TRAZO Y REPLANTEO
B45: 01.05.01 | C45: TRAZO NIVELACION Y REPLANTEO INICIAL | D45: m2 | J45: 405.11
B46: 01.05.02 | C46: TRAZO NIVELACION Y REPLANTEO DURANTE EL PROCESO | D46: m2 | J46: 101.28
B47: 2 | C47: ESTRUCTURAS
B48: 02.01 | C48: CREMATORIO
B49: 02.01.01 | C49: MOVIMIENTO DE TIERRAS
B50: 02.01.01.01 | C50: CORTE DE TERRENO PARA ADOQUINADO | D50: m3 | J50: 11.53
B51: 02.01.01.02 | C51: REFINE, NIVELACION Y COMPACTACION DE TERRENO NATURAL | D51: m2 | J51: 28.82
B52: 02.01.01.03 | C52: ACARREO INTERNO DE MATERIAL PROCEDENTE DEL CORTE (ADOQUINADO+CREMATORIO) | D52: m3 | J52: 122.48
B53: 02.01.01.04 | C53: ELIMINACION DE MATERIAL EXCEDENTE (ADOQUINADO+CREMATORIO) | D53: m3 | J53: 146.97
B54: 02.01.01.05 | C54: CORTE DE TERRENO PARA CREMATORIO | D54: m3 | J54: 55.8
B55: 02.01.01.06 | C55: REFINE, NIVELACION Y COMPACTACION DE TERRENO NATURAL | D55: m2 | J55: 139.5
B56: 02.01.01.07 | C56: EXCAVACION MANUAL EN TERRENO NORMAL | D56: m3 | J56: 55.15
B57: 02.01.01.08 | C57: RELLENO CON MATERIAL DE PRESTAMO (AFIRMADO) | D57: m3
B58: 02.01.02 | C58: OBRAS DE CONCRETO SIMPLE
B59: 02.01.02.01 | C59: SOLADO e=4" (ZAPATAS) | D59: m2 | J59: 29.4
B60: 02.01.03 | C60: OBRAS DE CONCRETO ARMADO
B61: 02.01.03.01 | C61: ZAPATAS AISLADAS
B62: 02.01.03.01.01 | C62: CONCRETO f'c=210 kg/cm2 - ZAPATAS | D62: m3 | J62: 17.33
B63: 02.01.03.01.02 | C63: ACERO DE REFUERZO fy=4,200 kg/cm2 | D63: kg | J63: 1529.4
B64: 02.01.03.01.03 | C64: CURADO DE CONCRETO | D64: m2 | J64: 48.89
B65: 02.01.03.02 | C65: COLUMNAS
B66: 02.01.03.02.03 | C66: ACERO DE REFUERZO fy=4,200 kg/cm2 | D66: kg | J66: 1886.58
B67: 02.03 | C67: COLUMBARIO
B68: 02.03.01 | C68: MOVIMIENTO DE TIERRAS
B69: 02.03.01.01 | C69: EXCAVACIONES SIMPLES
B70: 02.03.01.01.01 | C70: EXCAVACIONES SIMPLES PARA PLATEA DE CIMENTACION | D70: m3 | J70: 93.62
B71: 02.03.01.02 | C71: RELLENOS CON MATERIAL DE PRESTAMO
B72: 02.03.01.02.01 | C72: RELLENO PARA PLATEA DE CIMENTACION | D72: m3
B73: 02.03.01.03 | C73: ELIMINACIÓN DE MATERIAL EXCEDENTE
B74: 02.03.01.03.01 | C74: ELIMINACION DE MATERIAL EXCEDENTE C/VOLQ. 15M3, D=10km | D74: m3 | J74: 102.98
B75: 02.04 | C75: SC SUMINISTRO E INSTALACION DE HORNO DE CREMACION Y ELEMENTOS COMPLEMENTARIOS
B76: 02.04.01 | C76: SC SUMINISTRO E INSTALACION DE HORNO DE CREMACION Y ELEMENTOS COMPLEMENTARIOS | D76: glb | J76: 0.5

Sheet CURVA S
B2: VALORIZACIÓN N° 03 (01 AL 31 DE DICIEMBRE DE 2025)
B4: CURVA "S"
F26: PROGRAMADO | H26: EJECUTADO
F27: % Programado | G27: % programado acum. | H27: % Ejecutado | I27: % ejecutado acum. | N27: % Programado
E28: INICIO | F28: 0 | G28: 0 | H28: 0 | I28: 0 | N28: 0
E29: 45939 | F29: 0.17555412 | G29: =+G28+F29 -> 0.17555412 | H29: 0.2253999 | I29: =+I28+H29 -> 0.2253999 | N29: 0.17555412
E30: 45962 | F30: 0.1778155 | G30: =+G29+F30 -> 0.35336962 | H30: =+H62 -> 0.35859954 | I30: =+I29+H30 -> 0.58399944 | N30: 0.1778155
E31: 45992 | F31: 0.28006745 | G31: =+G30+F31 -> 0.63343707 | H31: =+H63 -> 0.14147619 | I31: =+I30+H31 -> 0.72547563 | N31: 0.28006745
E32: 46023 | F32: 0.21632749 | G32: =+G31+F32 -> 0.84976456 | N32: 0.21632749
E33: 46054 | F33: 0.15023544 | G33: =+G32+F33 -> 1 | N33: 0.15023544
G34: =+G33 -> 1 | I34: =+I31 -> 0.72547563
B36: GRÁFICO DE BARRAS
F58: PROGRAMADO | H58: EJECUTADO
F59: % Programado | G59: % programado acum. | H59: % Ejecutado | I59: % ejecutado acum.
E60: INICIO | F60: 0 | G60: 0 | H60: 0 | I60: 0
E61: 45939 | F61: 0.17555412 | G61: =+G60+F61 -> 0.17555412 | H61: =+'C.G. AVANCE DE OBRA'!J14 -> 0.2253999 | I61: =+I60+H61 -> 0.2253999
E62: 45962 | F62: 0.1778155 | G62: =+G61+F62 -> 0.35336962 | H62: =+'C.G. AVANCE DE OBRA'!J15 -> 0.35859954 | I62: =+I61+H62 -> 0.58399944
E63: 45992 | F63: 0.28006745 | G63: =+G62+F63 -> 0.63343707 | H63: =+'C.G. AVANCE DE OBRA'!J16 -> 0.14147619 | I63: =+I62+H63 -> 0.72547563
E64: 46023 | F64: 0.21632749 | G64: =+G63+F64 -> 0.84976456
E65: 46054 | F65: 0.15023544 | G65: =+G64+F65 -> 1
G66: =+G65 -> 1 | I66: =+I63 -> 0.72547563

Sheet K
A3: CÁLCULO DEL COEFICIENTE DE REAJUSTE
A5: OBRA: | C5: =+FICHA!E4 -> "CONSTRUCCION DE NICHO, COLUMBARIO Y CREMATORIO; REMODELACION DE VELATORIO; EN EL (LA) CEMENTERIO MUNICIPAL EN EL CENTRO POBLADO SANTIAGO DE SURCO, DISTRITO DE SANTIAGO DE SURCO, PROVINCIA LIMA, DEPARTAMENTO LIMA" CUI N| 2658565 - ETAPA COLUMBARIO.
A6: AS Nº | C6: =+FICHA!E15 -> 004-2025-CS-MSS-PRIMERA CONVOCATORIA
A7: ENTIDAD: | C7: =+FICHA!E8 -> MUNICIPALIDAD DISTRITAL DE SANTIAGO DE SURCO
A8: PPTO. BASE | C8: =+FICHA!E20 -> 1730120.8 | E8: INC. IGV
A9: PRESUPUESTO CONTRATADO | C9: =+FICHA!E18 -> 1821179.8 | E9: INC. IGV
A10: FECHA DE PRESUPUESTO BASE | C10: 45536
A12: Formula Polinomica
A13: K = 0.173*(Jr / Jo) + 0.201 *(Ar / Ao) + 0.132*(Cr / Co) + 0.369*(DMr / DMo) + 0.125*GGUr / GGUo)
A16: MONOMIO | B16: IU | C16: DESCRIPCION | D16: SIMBOLO | E16: Coeficiente de Incidencia | F16: % de Participación | G16: Io (OCT-2023) | H16: Ir (MAR.-2024) | I16: Ir (ABR.-2024)
A18: 1 | B18: 47 | C18: MANO DE OBRA INC LEYES SOCIALES | D18: J | E18: 0.173 | F18: 1 | G18: 738.61 | H18: 742.39 | I18: =+ROUND($E18*(H18/$G18)*F18,3) -> 0.174
A19: 2 | B19: 11 | C19: ARTEFACTO ILUMINACION EXTERIOR | D19: AG | E19: 0.201 | F19: 1 | G19: 273.17 | H19: 264.67 | I19: =+ROUND($E19*(H19/$G19)*F19,3) -> 0.195
A20: 3 | B20: 19 | C20: CABLES TIPO NKY-NYY | D20: C | E20: 0.132 | F20: 1 | G20: 1049.03 | H20: 1041.44 | I20: =+ROUND($E20*(H20/$G20)*F20,3) -> 0.131
A21: 4 | B21: 30 | C21: DÓLAR + INFLACION USA | D21: DM | E21: 0.369 | F21: 0.87263 | G21: 689.99 | H21: 671.28 | I21: 0.359
B22: 49 | C22: MAQUINARIA Y EQUIPO IMPORTADO | D22: MD | F22: 0.12737 | G22: 440.33 | H22: 432.41
A23: 5 | B23: 39 | C23: INDICE GENERAL DE PRECIOS AL CONSUMIDOR | D23: GGU | E23: 0.125 | F23: 1 | G23: 558.37 | H23: 568.63 | I23: =+ROUND($E23*(H23/$G23)*F23,3) -> 0.127
D24: K= | E24: =+SUM(E18:E23) -> 1 | I24: =SUM(I18:I23) -> 0.986
B26: *Se usa los IU del mes de agosto porque aún no se publican los IU de septiembre 2023
H29: =H21/G21*F21*0.369 -> 0.313269
H30: =H22/G22*0.369*F22 -> 0.046154172
E31: =H18/G18*E18*F18 -> 0.17388537 | H31: =H29+H30 -> 0.35942317
K33: 5
K34: 13
K35: 48
K36: 30
K37: 39

Sheet Reajuste
A4: CÁLCULO DEL COEFICIENTE DE REAJUSTE
A6: OBRA: | D6: =+K!C5 -> "CONSTRUCCION DE NICHO, COLUMBARIO Y CREMATORIO; REMODELACION DE VELATORIO; EN EL (LA) CEMENTERIO MUNICIPAL EN EL CENTRO POBLADO SANTIAGO DE SURCO, DISTRITO DE SANTIAGO DE SURCO, PROVINCIA LIMA, DEPARTAMENTO LIMA" CUI N| 2658565 - ETAPA COLUMBARIO.
A7: AS Nº | D7: =+K!C6 -> 004-2025-CS-MSS-PRIMERA CONVOCATORIA
A8: ENTIDAD: | D8: =+FICHA!E8 -> MUNICIPALIDAD DISTRITAL DE SANTIAGO DE SURCO
A9: PPTO. BASE | D9: =+FICHA!E18 -> 1821179.8 | F9: INC. IGV
A10: PRESUPUESTO CONTRATADO | D10: =+FICHA!E20 -> 1730120.8 | F10: INC. IGV
A11: PRESUPUESTO CONTRATADO S/IGV | D11: =+D10/1.18 -> 1466204.1 | F11: SIN. IGV
A12: FECHA DE PRESUPUESTO BASE | D12: 45203
A13: Formula Polinomica
B15: K = 0.173*(Jr / Jo) + 0.201 *(Ar / Ao) + 0.132*(Cr / Co) + 0.369*(DMr / DMo) + 0.125*GGUr / GGUo)
F18: R = V * ( K - 1)
A20: MESES | B20: VAL N° | C20: V-REAL | D20: V-PROG | E20: K - 1 | F20: REAJUSTE | G20: REAJUSTE | H20: REAJUSTE | I20: Vr | J20: REAJUSTE
F21: REAL | G21: PROGRAMADO | H21: RECONOCIDO | J21: PAGADO
C22: ( 1 ) | D22: ( 2 ) | E22: ( 3 ) | F22: ( 4 ) = ( 1 ) * ( 3 ) | G22: ( 5 ) = ( 2 ) * ( 3 ) | H22: ( 6 ) | I22: ( 7 ) = ( 1 ) + ( 6 ) | J22: (8)
A24: 45291 | B24: 1 | C24: =+VALO!K565 -> 207432.97 | D24: 569004.97 | E24: =+K!I24-1 -> -0.014 | F24: =+E24*C24 -> -2904.0616 | G24: =+ROUND(E24*D24,2) -> -7966.07 | H24: =+F24 -> -2904.0616 | I24: =ROUND(+C24+H24,2) -> 204528.91 | J24: =+H24 -> -2904.0616
A25: SUB-TOTAL | C25: =SUM(C24:C24) -> 207432.97 | F25: =SUM(F24:F24) -> -2904.0616 | G25: =SUM(G24:G24) -> -7966.07 | H25: =SUM(H24:H24) -> -2904.0616 | J25: 0
C27: CONDICION : | F27: Normal | J27: =SUMA(J24:J24)
C28: Reajuste Acumulado actual : | E28: S/. | F28: =+F29+J25 -> 0
C29: Reajuste Acumulado Anterior : | E29: S/. | F29: 0
C30: Reajuste Presente valorización: | E30: S/. | F30: =+J25 -> 0
E42: V-PROG | F42: V-PROG-MOD
D43: 44136 | E43: =+#REF! -> #REF! | F43: =+E43 -> #REF!
D44: 44166 | E44: =+#REF! -> #REF! | F44: =+E44*22/31 -> #REF!
D45: 44166 | F45: =+E44*0.290322580645161 -> #REF!
D46: 44197 | E46: =+#REF! -> #REF! | F46: =+E46 -> #REF!
D47: 44228 | E47: =+#REF! -> #REF! | F47: =+E47 -> #REF!
D48: 44256 | E48: =+#REF! -> #REF! | F48: =+E48 -> #REF!
D49: 44287 | E49: =+#REF! -> #REF! | F49: =+E49 -> #REF!
E50: =SUM(E43:E49) -> #REF! | F50: =SUM(F43:F49) -> #REF!
A54: 12715.178
